{
  "updated_at": "2026-06-02T17:01+09:00",
  "market": "KOSPI+KOSDAQ",
  "last_seen": "20260602000403",
  "disclosures": [
    {
      "rcept_no": "20260602000403",
      "rcept_dt": "2026-06-02",
      "corp_name": "SIMPAC",
      "stock_code": "009160",
      "market": "KOSPI",
      "corp_code": "00138260",
      "repror": "최민찬",
      "ofcps": "부사장",
      "rgist": "비등기임원",
      "main_shrholdr": "10%이상주주",
      "irds_cnt": "10,200",
      "total_cnt": "14,247,408",
      "irds_rate": "0.01",
      "hold_rate": "21.79",
      "method": "장내매수"
    },
    {
      "rcept_no": "20260602000400",
      "rcept_dt": "2026-06-02",
      "corp_name": "알엔티엑스",
      "stock_code": "123010",
      "market": "KOSDAQ",
      "corp_code": "00615723",
      "repror": "위드윈투자조합91호",
      "ofcps": "-",
      "rgist": "-",
      "main_shrholdr": "10%이상주주",
      "irds_cnt": "4,065,867",
      "total_cnt": "4,065,867",
      "irds_rate": "12.09",
      "hold_rate": "12.09",
      "method": "장외매수"
    },
    {
      "rcept_no": "20260602000381",
      "rcept_dt": "2026-06-02",
      "corp_name": "메가터치",
      "stock_code": "446540",
      "market": "KOSDAQ",
      "corp_code": "00923516",
      "repror": "최우용",
      "ofcps": "상무이사",
      "rgist": "등기임원",
      "main_shrholdr": "-",
      "irds_cnt": "1,267",
      "total_cnt": "16,003",
      "irds_rate": "0.01",
      "hold_rate": "0.06",
      "method": "장내매수"
    },
    {
      "rcept_no": "20260602000351",
      "rcept_dt": "2026-06-02",
      "corp_name": "일신바이오",
      "stock_code": "068330",
      "market": "KOSDAQ",
      "corp_code": "00385415",
      "repror": "홍중기",
      "ofcps": "이사",
      "rgist": "등기임원",
      "main_shrholdr": "사실상지배주주",
      "irds_cnt": "394,758",
      "total_cnt": "811,433",
      "irds_rate": "0.90",
      "hold_rate": "1.84",
      "method": "장내매수"
    },
    {
      "rcept_no": "20260602000344",
      "rcept_dt": "2026-06-02",
      "corp_name": "선바이오",
      "stock_code": "067370",
      "market": "KOSDAQ",
      "corp_code": "00407036",
      "repror": "노광",
      "ofcps": "대표이사",
      "rgist": "등기임원",
      "main_shrholdr": "사실상지배주주",
      "irds_cnt": "4,200",
      "total_cnt": "3,212,190",
      "irds_rate": "0.03",
      "hold_rate": "26.34",
      "method": "장내매수"
    },
    {
      "rcept_no": "20260602000324",
      "rcept_dt": "2026-06-02",
      "corp_name": "KTcs",
      "stock_code": "058850",
      "market": "KOSPI",
      "corp_code": "00372882",
      "repror": "이창호",
      "ofcps": "대표이사",
      "rgist": "등기임원",
      "main_shrholdr": "-",
      "irds_cnt": "10,000",
      "total_cnt": "10,000",
      "irds_rate": "0.02",
      "hold_rate": "0.02",
      "method": "장내매수"
    },
    {
      "rcept_no": "20260602000307",
      "rcept_dt": "2026-06-02",
      "corp_name": "삼익THK",
      "stock_code": "004380",
      "market": "KOSPI",
      "corp_code": "00127802",
      "repror": "류영수",
      "ofcps": "대표이사\n사장",
      "rgist": "등기임원",
      "main_shrholdr": "-",
      "irds_cnt": "2,500",
      "total_cnt": "10,000",
      "irds_rate": "0.01",
      "hold_rate": "0.05",
      "method": "장내매수"
    },
    {
      "rcept_no": "20260602000295",
      "rcept_dt": "2026-06-02",
      "corp_name": "보원케미칼",
      "stock_code": "0010F0",
      "market": "KOSDAQ",
      "corp_code": "00871587",
      "repror": "이현용",
      "ofcps": "사외이사",
      "rgist": "등기임원",
      "main_shrholdr": "-",
      "irds_cnt": "300",
      "total_cnt": "300",
      "irds_rate": "0.00",
      "hold_rate": "0.00",
      "method": "장내매수"
    },
    {
      "rcept_no": "20260602000291",
      "rcept_dt": "2026-06-02",
      "corp_name": "대신밸류리츠",
      "stock_code": "0030R0",
      "market": "KOSPI",
      "corp_code": "01885222",
      "repror": "대신증권",
      "ofcps": "-",
      "rgist": "-",
      "main_shrholdr": "10%이상주주",
      "irds_cnt": "13,497",
      "total_cnt": "11,073,589",
      "irds_rate": "0.02",
      "hold_rate": "18.52",
      "method": "장내매수"
    },
    {
      "rcept_no": "20260602000266",
      "rcept_dt": "2026-06-02",
      "corp_name": "라파스",
      "stock_code": "214260",
      "market": "KOSDAQ",
      "corp_code": "01058101",
      "repror": "하기완",
      "ofcps": "의약품사업본부장",
      "rgist": "비등기임원",
      "main_shrholdr": "-",
      "irds_cnt": "1,136",
      "total_cnt": "1,136",
      "irds_rate": "0.01",
      "hold_rate": "0.01",
      "method": "장내매수"
    },
    {
      "rcept_no": "20260602000259",
      "rcept_dt": "2026-06-02",
      "corp_name": "씨큐브",
      "stock_code": "101240",
      "market": "KOSDAQ",
      "corp_code": "00520610",
      "repror": "스타치얼코퍼레이션",
      "ofcps": "-",
      "rgist": "-",
      "main_shrholdr": "10%이상주주",
      "irds_cnt": "135,599",
      "total_cnt": "4,448,299",
      "irds_rate": "-0.54",
      "hold_rate": "39.17",
      "method": "장내매수"
    },
    {
      "rcept_no": "20260602000255",
      "rcept_dt": "2026-06-02",
      "corp_name": "제이엔케이글로벌",
      "stock_code": "126880",
      "market": "KOSDAQ",
      "corp_code": "00442154",
      "repror": "최창윤",
      "ofcps": "부사장",
      "rgist": "등기임원",
      "main_shrholdr": "-",
      "irds_cnt": "15,000",
      "total_cnt": "153,500",
      "irds_rate": "0.06",
      "hold_rate": "0.66",
      "method": "장내매수"
    },
    {
      "rcept_no": "20260602000179",
      "rcept_dt": "2026-06-02",
      "corp_name": "INVENI",
      "stock_code": "015360",
      "market": "KOSPI",
      "corp_code": "00105101",
      "repror": "구자은",
      "ofcps": "-",
      "rgist": "-",
      "main_shrholdr": "사실상지배주주",
      "irds_cnt": "3,709",
      "total_cnt": "2,419,434",
      "irds_rate": "0.01",
      "hold_rate": "8.88",
      "method": "장내매수"
    },
    {
      "rcept_no": "20260602000150",
      "rcept_dt": "2026-06-02",
      "corp_name": "삼성전자",
      "stock_code": "005930",
      "market": "KOSPI",
      "corp_code": "00126380",
      "repror": "최인수",
      "ofcps": "상무",
      "rgist": "비등기임원",
      "main_shrholdr": "-",
      "irds_cnt": "1,178",
      "total_cnt": "1,178",
      "irds_rate": "0.00",
      "hold_rate": "0.00",
      "method": "장내매수"
    },
    {
      "rcept_no": "20260602000138",
      "rcept_dt": "2026-06-02",
      "corp_name": "오토앤",
      "stock_code": "353590",
      "market": "KOSDAQ",
      "corp_code": "01084294",
      "repror": "최찬욱",
      "ofcps": "대표이사",
      "rgist": "등기임원",
      "main_shrholdr": "사실상지배주주",
      "irds_cnt": "5,000",
      "total_cnt": "1,736,188",
      "irds_rate": "0.04",
      "hold_rate": "13.18",
      "method": "장내매수"
    },
    {
      "rcept_no": "20260602000135",
      "rcept_dt": "2026-06-02",
      "corp_name": "한국주철관공업",
      "stock_code": "000970",
      "market": "KOSPI",
      "corp_code": "00159573",
      "repror": "김태형",
      "ofcps": "대표이사",
      "rgist": "등기임원",
      "main_shrholdr": "-",
      "irds_cnt": "68,469",
      "total_cnt": "2,091,184",
      "irds_rate": "0.30",
      "hold_rate": "9.17",
      "method": "장내매수"
    },
    {
      "rcept_no": "20260602000104",
      "rcept_dt": "2026-06-02",
      "corp_name": "iM금융지주",
      "stock_code": "139130",
      "market": "KOSPI",
      "corp_code": "00878915",
      "repror": "이창영",
      "ofcps": "전무",
      "rgist": "비등기임원",
      "main_shrholdr": "-",
      "irds_cnt": "1,000",
      "total_cnt": "24,000",
      "irds_rate": "0.00",
      "hold_rate": "0.01",
      "method": "장내매수"
    },
    {
      "rcept_no": "20260602000100",
      "rcept_dt": "2026-06-02",
      "corp_name": "디알텍",
      "stock_code": "214680",
      "market": "KOSDAQ",
      "corp_code": "01062867",
      "repror": "안성현",
      "ofcps": "대표이사\n(CEO)",
      "rgist": "등기임원",
      "main_shrholdr": "-",
      "irds_cnt": "7,137",
      "total_cnt": "3,093,552",
      "irds_rate": "-0.42",
      "hold_rate": "3.50",
      "method": "장내매수"
    },
    {
      "rcept_no": "20260602000098",
      "rcept_dt": "2026-06-02",
      "corp_name": "에스트래픽",
      "stock_code": "234300",
      "market": "KOSDAQ",
      "corp_code": "01014055",
      "repror": "이장한",
      "ofcps": "부사장",
      "rgist": "비등기임원",
      "main_shrholdr": "-",
      "irds_cnt": "10,000",
      "total_cnt": "40,000",
      "irds_rate": "0.04",
      "hold_rate": "0.15",
      "method": "장내매수"
    },
    {
      "rcept_no": "20260602000091",
      "rcept_dt": "2026-06-02",
      "corp_name": "대성미생물",
      "stock_code": "036480",
      "market": "KOSDAQ",
      "corp_code": "00177320",
      "repror": "인실리코",
      "ofcps": "-",
      "rgist": "-",
      "main_shrholdr": "사실상지배주주",
      "irds_cnt": "8,688",
      "total_cnt": "1,490,982",
      "irds_rate": "0.23",
      "hold_rate": "39.24",
      "method": "장내매수"
    },
    {
      "rcept_no": "20260602000078",
      "rcept_dt": "2026-06-02",
      "corp_name": "이엠텍",
      "stock_code": "091120",
      "market": "KOSDAQ",
      "corp_code": "00541163",
      "repror": "최동규",
      "ofcps": "상근감사",
      "rgist": "등기임원",
      "main_shrholdr": "-",
      "irds_cnt": "3,884",
      "total_cnt": "3,884",
      "irds_rate": "0.02",
      "hold_rate": "0.02",
      "method": "장내매수"
    },
    {
      "rcept_no": "20260602000065",
      "rcept_dt": "2026-06-02",
      "corp_name": "웨이버스",
      "stock_code": "336060",
      "market": "KOSDAQ",
      "corp_code": "01408999",
      "repror": "김학성",
      "ofcps": "대표이사",
      "rgist": "등기임원",
      "main_shrholdr": "10%이상주주",
      "irds_cnt": "152,387",
      "total_cnt": "12,155,411",
      "irds_rate": "0.31",
      "hold_rate": "25.24",
      "method": "장내매수"
    },
    {
      "rcept_no": "20260602000042",
      "rcept_dt": "2026-06-02",
      "corp_name": "DS단석",
      "stock_code": "017860",
      "market": "KOSPI",
      "corp_code": "00108612",
      "repror": "한수현",
      "ofcps": "부사장",
      "rgist": "비등기임원",
      "main_shrholdr": "-",
      "irds_cnt": "95,500",
      "total_cnt": "709,767",
      "irds_rate": "0.54",
      "hold_rate": "4.00",
      "method": "장내매수"
    },
    {
      "rcept_no": "20260601001932",
      "rcept_dt": "2026-06-01",
      "corp_name": "더네이쳐홀딩스",
      "stock_code": "298540",
      "market": "KOSDAQ",
      "corp_code": "01214743",
      "repror": "박영준",
      "ofcps": "대표이사",
      "rgist": "등기임원",
      "main_shrholdr": "사실상지배주주",
      "irds_cnt": "10,000",
      "total_cnt": "3,278,470",
      "irds_rate": "0.07",
      "hold_rate": "22.63",
      "method": "장내매수"
    },
    {
      "rcept_no": "20260601001891",
      "rcept_dt": "2026-06-01",
      "corp_name": "케이티스카이라이프",
      "stock_code": "053210",
      "market": "KOSPI",
      "corp_code": "00349097",
      "repror": "지정용",
      "ofcps": "사장",
      "rgist": "등기임원",
      "main_shrholdr": "-",
      "irds_cnt": "10,000",
      "total_cnt": "10,000",
      "irds_rate": "0.02",
      "hold_rate": "0.02",
      "method": "장내매수"
    },
    {
      "rcept_no": "20260601001851",
      "rcept_dt": "2026-06-01",
      "corp_name": "파라텍",
      "stock_code": "033540",
      "market": "KOSDAQ",
      "corp_code": "00105138",
      "repror": "김선복",
      "ofcps": "전무이사",
      "rgist": "비등기임원",
      "main_shrholdr": "-",
      "irds_cnt": "56,072",
      "total_cnt": "56,072",
      "irds_rate": "0.11",
      "hold_rate": "0.11",
      "method": "장내매수"
    },
    {
      "rcept_no": "20260601001845",
      "rcept_dt": "2026-06-01",
      "corp_name": "파라텍",
      "stock_code": "033540",
      "market": "KOSDAQ",
      "corp_code": "00105138",
      "repror": "박선기",
      "ofcps": "대표이사",
      "rgist": "등기임원",
      "main_shrholdr": "-",
      "irds_cnt": "94,194",
      "total_cnt": "94,194",
      "irds_rate": "0.18",
      "hold_rate": "0.18",
      "method": "장내매수"
    },
    {
      "rcept_no": "20260601001839",
      "rcept_dt": "2026-06-01",
      "corp_name": "유한양행",
      "stock_code": "000100",
      "market": "KOSPI",
      "corp_code": "00145109",
      "repror": "이병만",
      "ofcps": "부사장",
      "rgist": "비등기임원",
      "main_shrholdr": "-",
      "irds_cnt": "200",
      "total_cnt": "3,432",
      "irds_rate": "0.00",
      "hold_rate": "0.00",
      "method": "장내매수"
    },
    {
      "rcept_no": "20260601001732",
      "rcept_dt": "2026-06-01",
      "corp_name": "에이루트",
      "stock_code": "096690",
      "market": "KOSDAQ",
      "corp_code": "00608839",
      "repror": "이대성",
      "ofcps": "사내이사",
      "rgist": "등기임원",
      "main_shrholdr": "-",
      "irds_cnt": "9,018",
      "total_cnt": "50,547",
      "irds_rate": "0.23",
      "hold_rate": "1.26",
      "method": "장내매수"
    },
    {
      "rcept_no": "20260601001534",
      "rcept_dt": "2026-06-01",
      "corp_name": "유안타증권",
      "stock_code": "003470",
      "market": "KOSPI",
      "corp_code": "00117601",
      "repror": "최해호",
      "ofcps": "상무",
      "rgist": "비등기임원",
      "main_shrholdr": "-",
      "irds_cnt": "500",
      "total_cnt": "13,886",
      "irds_rate": "0.00",
      "hold_rate": "0.01",
      "method": "장내매수"
    },
    {
      "rcept_no": "20260601001495",
      "rcept_dt": "2026-06-01",
      "corp_name": "신영증권",
      "stock_code": "001720",
      "market": "KOSPI",
      "corp_code": "00136721",
      "repror": "원종석",
      "ofcps": "사내이사",
      "rgist": "등기임원",
      "main_shrholdr": "사실상지배주주",
      "irds_cnt": "7,815",
      "total_cnt": "1,361,320",
      "irds_rate": "0.05",
      "hold_rate": "8.28",
      "method": "장내매수"
    },
    {
      "rcept_no": "20260601001481",
      "rcept_dt": "2026-06-01",
      "corp_name": "한미약품",
      "stock_code": "128940",
      "market": "KOSPI",
      "corp_code": "00828497",
      "repror": "국민연금공단",
      "ofcps": "-",
      "rgist": "-",
      "main_shrholdr": "10%이상주주",
      "irds_cnt": "1,281,813",
      "total_cnt": "1,281,813",
      "irds_rate": "10.01",
      "hold_rate": "10.01",
      "method": "장내매수"
    },
    {
      "rcept_no": "20260601001474",
      "rcept_dt": "2026-06-01",
      "corp_name": "E8",
      "stock_code": "418620",
      "market": "KOSDAQ",
      "corp_code": "01516890",
      "repror": "이호선",
      "ofcps": "이사",
      "rgist": "비등기임원",
      "main_shrholdr": "-",
      "irds_cnt": "1,070",
      "total_cnt": "7,531",
      "irds_rate": "0.01",
      "hold_rate": "0.04",
      "method": "장내매수"
    },
    {
      "rcept_no": "20260601001472",
      "rcept_dt": "2026-06-01",
      "corp_name": "LIG디펜스앤에어로스페이스",
      "stock_code": "079550",
      "market": "KOSPI",
      "corp_code": "00503668",
      "repror": "국민연금공단",
      "ofcps": "-",
      "rgist": "-",
      "main_shrholdr": "10%이상주주",
      "irds_cnt": "2,212,945",
      "total_cnt": "2,212,945",
      "irds_rate": "10.06",
      "hold_rate": "10.06",
      "method": "장내매수"
    },
    {
      "rcept_no": "20260601001463",
      "rcept_dt": "2026-06-01",
      "corp_name": "HL만도",
      "stock_code": "204320",
      "market": "KOSPI",
      "corp_code": "01042775",
      "repror": "국민연금공단",
      "ofcps": "-",
      "rgist": "-",
      "main_shrholdr": "10%이상주주",
      "irds_cnt": "4,760,920",
      "total_cnt": "4,760,920",
      "irds_rate": "10.14",
      "hold_rate": "10.14",
      "method": "장내매수"
    },
    {
      "rcept_no": "20260601001457",
      "rcept_dt": "2026-06-01",
      "corp_name": "금호석유화학",
      "stock_code": "011780",
      "market": "KOSPI",
      "corp_code": "00106368",
      "repror": "국민연금공단",
      "ofcps": "-",
      "rgist": "-",
      "main_shrholdr": "10%이상주주",
      "irds_cnt": "2,772,299",
      "total_cnt": "2,772,299",
      "irds_rate": "9.84",
      "hold_rate": "9.84",
      "method": "장내매수"
    },
    {
      "rcept_no": "20260601001451",
      "rcept_dt": "2026-06-01",
      "corp_name": "현대코퍼레이션",
      "stock_code": "011760",
      "market": "KOSPI",
      "corp_code": "00164812",
      "repror": "현대코퍼레이션홀딩스",
      "ofcps": "-",
      "rgist": "-",
      "main_shrholdr": "10%이상주주",
      "irds_cnt": "606,361",
      "total_cnt": "3,168,361",
      "irds_rate": "4.58",
      "hold_rate": "23.95",
      "method": "장내매수"
    },
    {
      "rcept_no": "20260601001447",
      "rcept_dt": "2026-06-01",
      "corp_name": "효성티앤씨",
      "stock_code": "298020",
      "market": "KOSPI",
      "corp_code": "01316227",
      "repror": "국민연금공단",
      "ofcps": "-",
      "rgist": "-",
      "main_shrholdr": "10%이상주주",
      "irds_cnt": "5,062",
      "total_cnt": "472,524",
      "irds_rate": "0.12",
      "hold_rate": "10.92",
      "method": "장내매수"
    },
    {
      "rcept_no": "20260601001437",
      "rcept_dt": "2026-06-01",
      "corp_name": "삼양식품",
      "stock_code": "003230",
      "market": "KOSPI",
      "corp_code": "00126955",
      "repror": "국민연금공단",
      "ofcps": "-",
      "rgist": "-",
      "main_shrholdr": "10%이상주주",
      "irds_cnt": "11,310",
      "total_cnt": "795,114",
      "irds_rate": "0.16",
      "hold_rate": "10.56",
      "method": "장내매수"
    },
    {
      "rcept_no": "20260601001398",
      "rcept_dt": "2026-06-01",
      "corp_name": "서연탑메탈",
      "stock_code": "019770",
      "market": "KOSDAQ",
      "corp_code": "00153278",
      "repror": "유경내",
      "ofcps": "사장",
      "rgist": "비등기임원",
      "main_shrholdr": "-",
      "irds_cnt": "25,000",
      "total_cnt": "1,100,000",
      "irds_rate": "0.21",
      "hold_rate": "9.44",
      "method": "장내매수"
    },
    {
      "rcept_no": "20260601001225",
      "rcept_dt": "2026-06-01",
      "corp_name": "에스에스알",
      "stock_code": "275630",
      "market": "KOSDAQ",
      "corp_code": "01250374",
      "repror": "지란지교시큐리티",
      "ofcps": "-",
      "rgist": "-",
      "main_shrholdr": "사실상지배주주",
      "irds_cnt": "12,000",
      "total_cnt": "2,490,356",
      "irds_rate": "0.23",
      "hold_rate": "47.40",
      "method": "장내매수"
    },
    {
      "rcept_no": "20260601001189",
      "rcept_dt": "2026-06-01",
      "corp_name": "미트박스",
      "stock_code": "475460",
      "market": "KOSDAQ",
      "corp_code": "01374717",
      "repror": "윤희성",
      "ofcps": "이사",
      "rgist": "비등기임원",
      "main_shrholdr": "-",
      "irds_cnt": "932",
      "total_cnt": "4,532",
      "irds_rate": "0.02",
      "hold_rate": "0.08",
      "method": "장내매수"
    },
    {
      "rcept_no": "20260601001159",
      "rcept_dt": "2026-06-01",
      "corp_name": "미트박스",
      "stock_code": "475460",
      "market": "KOSDAQ",
      "corp_code": "01374717",
      "repror": "김만섭",
      "ofcps": "상무이사",
      "rgist": "비등기임원",
      "main_shrholdr": "-",
      "irds_cnt": "5,000",
      "total_cnt": "11,000",
      "irds_rate": "0.08",
      "hold_rate": "0.19",
      "method": "장내매수"
    },
    {
      "rcept_no": "20260601001155",
      "rcept_dt": "2026-06-01",
      "corp_name": "미트박스",
      "stock_code": "475460",
      "market": "KOSDAQ",
      "corp_code": "01374717",
      "repror": "정재호",
      "ofcps": "전무이사",
      "rgist": "등기임원",
      "main_shrholdr": "-",
      "irds_cnt": "8,760",
      "total_cnt": "9,760",
      "irds_rate": "0.15",
      "hold_rate": "0.17",
      "method": "장내매수"
    },
    {
      "rcept_no": "20260601001147",
      "rcept_dt": "2026-06-01",
      "corp_name": "미트박스",
      "stock_code": "475460",
      "market": "KOSDAQ",
      "corp_code": "01374717",
      "repror": "천용헌",
      "ofcps": "부사장",
      "rgist": "등기임원",
      "main_shrholdr": "-",
      "irds_cnt": "15,133",
      "total_cnt": "29,242",
      "irds_rate": "0.27",
      "hold_rate": "0.52",
      "method": "장내매수"
    },
    {
      "rcept_no": "20260601001051",
      "rcept_dt": "2026-06-01",
      "corp_name": "가온전선",
      "stock_code": "000500",
      "market": "KOSPI",
      "corp_code": "00104768",
      "repror": "정현",
      "ofcps": "부사장\n(대표이사)",
      "rgist": "등기임원",
      "main_shrholdr": "-",
      "irds_cnt": "48",
      "total_cnt": "2,778",
      "irds_rate": "0.00",
      "hold_rate": "0.01",
      "method": "장내매수"
    },
    {
      "rcept_no": "20260601000964",
      "rcept_dt": "2026-06-01",
      "corp_name": "뉴로핏",
      "stock_code": "380550",
      "market": "KOSDAQ",
      "corp_code": "01782004",
      "repror": "빈준길",
      "ofcps": "공동대표이사",
      "rgist": "등기임원",
      "main_shrholdr": "10%이상주주",
      "irds_cnt": "2,000",
      "total_cnt": "1,187,600",
      "irds_rate": "-0.59",
      "hold_rate": "9.74",
      "method": "장내매수"
    },
    {
      "rcept_no": "20260601000947",
      "rcept_dt": "2026-06-01",
      "corp_name": "뉴로핏",
      "stock_code": "380550",
      "market": "KOSDAQ",
      "corp_code": "01782004",
      "repror": "김동현",
      "ofcps": "공동대표이사",
      "rgist": "등기임원",
      "main_shrholdr": "10%이상주주",
      "irds_cnt": "1,000",
      "total_cnt": "1,779,400",
      "irds_rate": "-0.91",
      "hold_rate": "14.59",
      "method": "장내매수"
    },
    {
      "rcept_no": "20260601000828",
      "rcept_dt": "2026-06-01",
      "corp_name": "에이치와이티씨",
      "stock_code": "148930",
      "market": "KOSDAQ",
      "corp_code": "00885906",
      "repror": "김승준",
      "ofcps": "상무이사",
      "rgist": "비등기임원",
      "main_shrholdr": "-",
      "irds_cnt": "691",
      "total_cnt": "691",
      "irds_rate": "0.01",
      "hold_rate": "0.01",
      "method": "장내매수"
    },
    {
      "rcept_no": "20260601000695",
      "rcept_dt": "2026-06-01",
      "corp_name": "삼일제약",
      "stock_code": "000520",
      "market": "KOSPI",
      "corp_code": "00128032",
      "repror": "한병익",
      "ofcps": "부 사 장",
      "rgist": "비등기임원",
      "main_shrholdr": "-",
      "irds_cnt": "1,000",
      "total_cnt": "7,058",
      "irds_rate": "-0.01",
      "hold_rate": "0.03",
      "method": "장내매수"
    },
    {
      "rcept_no": "20260601000656",
      "rcept_dt": "2026-06-01",
      "corp_name": "포인트모바일",
      "stock_code": "318020",
      "market": "KOSDAQ",
      "corp_code": "00962393",
      "repror": "강삼권",
      "ofcps": "-",
      "rgist": "-",
      "main_shrholdr": "10%이상주주",
      "irds_cnt": "32,392",
      "total_cnt": "3,887,959",
      "irds_rate": "1.02",
      "hold_rate": "29.42",
      "method": "장내매수"
    },
    {
      "rcept_no": "20260601000651",
      "rcept_dt": "2026-06-01",
      "corp_name": "에어레인",
      "stock_code": "163280",
      "market": "KOSDAQ",
      "corp_code": "01663116",
      "repror": "위정욱",
      "ofcps": "관리본부장/CFO",
      "rgist": "등기임원",
      "main_shrholdr": "-",
      "irds_cnt": "3",
      "total_cnt": "1,655",
      "irds_rate": "0",
      "hold_rate": "0.01",
      "method": "장내매수"
    },
    {
      "rcept_no": "20260601000584",
      "rcept_dt": "2026-06-01",
      "corp_name": "KB금융",
      "stock_code": "105560",
      "market": "KOSPI",
      "corp_code": "00688996",
      "repror": "박선현",
      "ofcps": "담당",
      "rgist": "비등기임원",
      "main_shrholdr": "-",
      "irds_cnt": "300",
      "total_cnt": "1,293",
      "irds_rate": "0.000",
      "hold_rate": "0.000",
      "method": "장내매수"
    },
    {
      "rcept_no": "20260601000469",
      "rcept_dt": "2026-06-01",
      "corp_name": "대성미생물",
      "stock_code": "036480",
      "market": "KOSDAQ",
      "corp_code": "00177320",
      "repror": "인실리코",
      "ofcps": "-",
      "rgist": "-",
      "main_shrholdr": "사실상지배주주",
      "irds_cnt": "6,468",
      "total_cnt": "1,482,294",
      "irds_rate": "0.17",
      "hold_rate": "39.01",
      "method": "장내매수"
    },
    {
      "rcept_no": "20260601000435",
      "rcept_dt": "2026-06-01",
      "corp_name": "일진파워",
      "stock_code": "094820",
      "market": "KOSDAQ",
      "corp_code": "00485177",
      "repror": "이상업",
      "ofcps": "회장",
      "rgist": "등기임원",
      "main_shrholdr": "-",
      "irds_cnt": "1,650",
      "total_cnt": "164,633",
      "irds_rate": "0.01",
      "hold_rate": "1.09",
      "method": "장내매수"
    },
    {
      "rcept_no": "20260601000385",
      "rcept_dt": "2026-06-01",
      "corp_name": "대성미생물",
      "stock_code": "036480",
      "market": "KOSDAQ",
      "corp_code": "00177320",
      "repror": "최승훈",
      "ofcps": "대표이사",
      "rgist": "등기임원",
      "main_shrholdr": "-",
      "irds_cnt": "4,027",
      "total_cnt": "37,900",
      "irds_rate": "0.11",
      "hold_rate": "1.00",
      "method": "장내매수"
    },
    {
      "rcept_no": "20260601000369",
      "rcept_dt": "2026-06-01",
      "corp_name": "삼성전자",
      "stock_code": "005930",
      "market": "KOSPI",
      "corp_code": "00126380",
      "repror": "김경석",
      "ofcps": "상무",
      "rgist": "비등기임원",
      "main_shrholdr": "-",
      "irds_cnt": "1",
      "total_cnt": "237",
      "irds_rate": "0.00",
      "hold_rate": "0.00",
      "method": "장내매수"
    },
    {
      "rcept_no": "20260601000356",
      "rcept_dt": "2026-06-01",
      "corp_name": "부스타",
      "stock_code": "008470",
      "market": "KOSDAQ",
      "corp_code": "00124276",
      "repror": "유덕기",
      "ofcps": "상무",
      "rgist": "비등기임원",
      "main_shrholdr": "-",
      "irds_cnt": "1,459",
      "total_cnt": "3,213",
      "irds_rate": "0.02",
      "hold_rate": "0.04",
      "method": "장내매수"
    },
    {
      "rcept_no": "20260601000269",
      "rcept_dt": "2026-06-01",
      "corp_name": "삼일제약",
      "stock_code": "000520",
      "market": "KOSPI",
      "corp_code": "00128032",
      "repror": "유담향",
      "ofcps": "전무",
      "rgist": "비등기임원",
      "main_shrholdr": "-",
      "irds_cnt": "1,000",
      "total_cnt": "12,000",
      "irds_rate": "-0.01",
      "hold_rate": "0.06",
      "method": "장내매수"
    },
    {
      "rcept_no": "20260601000195",
      "rcept_dt": "2026-06-01",
      "corp_name": "에어레인",
      "stock_code": "163280",
      "market": "KOSDAQ",
      "corp_code": "01663116",
      "repror": "하성용",
      "ofcps": "대표이사",
      "rgist": "등기임원",
      "main_shrholdr": "사실상지배주주",
      "irds_cnt": "9,884",
      "total_cnt": "2,285,724",
      "irds_rate": "0.07",
      "hold_rate": "16.80",
      "method": "장내매수"
    },
    {
      "rcept_no": "20260601000073",
      "rcept_dt": "2026-06-01",
      "corp_name": "아이센스",
      "stock_code": "099190",
      "market": "KOSDAQ",
      "corp_code": "00550994",
      "repror": "남학현",
      "ofcps": "대표이사(사장)",
      "rgist": "등기임원",
      "main_shrholdr": "-",
      "irds_cnt": "1,000",
      "total_cnt": "2,005,000",
      "irds_rate": "0.00",
      "hold_rate": "7.23",
      "method": "장내매수"
    },
    {
      "rcept_no": "20260601000034",
      "rcept_dt": "2026-06-01",
      "corp_name": "대창단조",
      "stock_code": "015230",
      "market": "KOSPI",
      "corp_code": "00112679",
      "repror": "박권일",
      "ofcps": "대표이사",
      "rgist": "등기임원",
      "main_shrholdr": "10%이상주주",
      "irds_cnt": "3,050",
      "total_cnt": "5,730,419",
      "irds_rate": "0.01",
      "hold_rate": "21.11",
      "method": "장내매수"
    },
    {
      "rcept_no": "20260601000001",
      "rcept_dt": "2026-06-01",
      "corp_name": "삼성전자",
      "stock_code": "005930",
      "market": "KOSPI",
      "corp_code": "00126380",
      "repror": "하지훈",
      "ofcps": "상무",
      "rgist": "비등기임원",
      "main_shrholdr": "-",
      "irds_cnt": "10",
      "total_cnt": "1,736",
      "irds_rate": "0",
      "hold_rate": "0",
      "method": "장내매수"
    },
    {
      "rcept_no": "20260529002359",
      "rcept_dt": "2026-05-29",
      "corp_name": "서울전자통신",
      "stock_code": "027040",
      "market": "KOSDAQ",
      "corp_code": "00130587",
      "repror": "에스이티 제2호 투자조합",
      "ofcps": "-",
      "rgist": "-",
      "main_shrholdr": "10%이상주주",
      "irds_cnt": "1,876,675",
      "total_cnt": "1,876,675",
      "irds_rate": "13.5",
      "hold_rate": "13.5",
      "method": "장외매수"
    },
    {
      "rcept_no": "20260529002347",
      "rcept_dt": "2026-05-29",
      "corp_name": "서울전자통신",
      "stock_code": "027040",
      "market": "KOSDAQ",
      "corp_code": "00130587",
      "repror": "에스이티 제1호 투자조합",
      "ofcps": "-",
      "rgist": "-",
      "main_shrholdr": "10%이상주주",
      "irds_cnt": "1,876,675",
      "total_cnt": "1,876,675",
      "irds_rate": "13.5",
      "hold_rate": "13.5",
      "method": "장외매수"
    },
    {
      "rcept_no": "20260529002338",
      "rcept_dt": "2026-05-29",
      "corp_name": "서울전자통신",
      "stock_code": "027040",
      "market": "KOSDAQ",
      "corp_code": "00130587",
      "repror": "다온인터내셔널",
      "ofcps": "-",
      "rgist": "-",
      "main_shrholdr": "10%이상주주",
      "irds_cnt": "2,073,196",
      "total_cnt": "2,073,196",
      "irds_rate": "14.9",
      "hold_rate": "14.9",
      "method": "장외매수"
    },
    {
      "rcept_no": "20260529002312",
      "rcept_dt": "2026-05-29",
      "corp_name": "우성머티리얼스",
      "stock_code": "011300",
      "market": "KOSPI",
      "corp_code": "00132868",
      "repror": "임종찬",
      "ofcps": "대표이사",
      "rgist": "등기임원",
      "main_shrholdr": "사실상지배주주",
      "irds_cnt": "2,150",
      "total_cnt": "157,150",
      "irds_rate": "0",
      "hold_rate": "0.99",
      "method": "장내매수"
    },
    {
      "rcept_no": "20260529002227",
      "rcept_dt": "2026-05-29",
      "corp_name": "해성디에스",
      "stock_code": "195870",
      "market": "KOSPI",
      "corp_code": "01032413",
      "repror": "김남석",
      "ofcps": "사외이사",
      "rgist": "등기임원",
      "main_shrholdr": "-",
      "irds_cnt": "180",
      "total_cnt": "180",
      "irds_rate": "0.00",
      "hold_rate": "0.00",
      "method": "장내매수"
    },
    {
      "rcept_no": "20260529002177",
      "rcept_dt": "2026-05-29",
      "corp_name": "미래에셋생명",
      "stock_code": "085620",
      "market": "KOSPI",
      "corp_code": "00112332",
      "repror": "미래에셋자산운용",
      "ofcps": "-",
      "rgist": "-",
      "main_shrholdr": "10%이상주주",
      "irds_cnt": "108,624",
      "total_cnt": "32,701,598",
      "irds_rate": "0.08",
      "hold_rate": "24.19",
      "method": "장내매수"
    },
    {
      "rcept_no": "20260529002106",
      "rcept_dt": "2026-05-29",
      "corp_name": "플래티어",
      "stock_code": "367000",
      "market": "KOSDAQ",
      "corp_code": "01454341",
      "repror": "김명구",
      "ofcps": "경영임원",
      "rgist": "등기임원",
      "main_shrholdr": "-",
      "irds_cnt": "6,526",
      "total_cnt": "29,114",
      "irds_rate": "0.08",
      "hold_rate": "0.35",
      "method": "장내매수"
    },
    {
      "rcept_no": "20260529002008",
      "rcept_dt": "2026-05-29",
      "corp_name": "국제약품",
      "stock_code": "002720",
      "market": "KOSPI",
      "corp_code": "00104722",
      "repror": "김영관",
      "ofcps": "부사장",
      "rgist": "등기임원",
      "main_shrholdr": "-",
      "irds_cnt": "2,000",
      "total_cnt": "35,000",
      "irds_rate": "0.01",
      "hold_rate": "0.17",
      "method": "장내매수"
    },
    {
      "rcept_no": "20260529001996",
      "rcept_dt": "2026-05-29",
      "corp_name": "플래티어",
      "stock_code": "367000",
      "market": "KOSDAQ",
      "corp_code": "01454341",
      "repror": "김진성",
      "ofcps": "경영임원",
      "rgist": "비등기임원",
      "main_shrholdr": "-",
      "irds_cnt": "811",
      "total_cnt": "40,668",
      "irds_rate": "0.00",
      "hold_rate": "0.48",
      "method": "장내매수"
    },
    {
      "rcept_no": "20260529001946",
      "rcept_dt": "2026-05-29",
      "corp_name": "메리츠금융지주",
      "stock_code": "138040",
      "market": "KOSPI",
      "corp_code": "00860332",
      "repror": "권동찬",
      "ofcps": "전무",
      "rgist": "비등기임원",
      "main_shrholdr": "-",
      "irds_cnt": "13",
      "total_cnt": "4,199",
      "irds_rate": "0.00",
      "hold_rate": "0.00",
      "method": "장내매수"
    },
    {
      "rcept_no": "20260529001927",
      "rcept_dt": "2026-05-29",
      "corp_name": "메리츠금융지주",
      "stock_code": "138040",
      "market": "KOSPI",
      "corp_code": "00860332",
      "repror": "여은석",
      "ofcps": "부사장",
      "rgist": "비등기임원",
      "main_shrholdr": "-",
      "irds_cnt": "16",
      "total_cnt": "4,977",
      "irds_rate": "0.00",
      "hold_rate": "0.00",
      "method": "장내매수"
    },
    {
      "rcept_no": "20260529001892",
      "rcept_dt": "2026-05-29",
      "corp_name": "하이트진로",
      "stock_code": "000080",
      "market": "KOSPI",
      "corp_code": "00150244",
      "repror": "박연규",
      "ofcps": "상무보",
      "rgist": "비등기임원",
      "main_shrholdr": "-",
      "irds_cnt": "800",
      "total_cnt": "2,500",
      "irds_rate": "0.00",
      "hold_rate": "0.00",
      "method": "장내매수"
    },
    {
      "rcept_no": "20260529001867",
      "rcept_dt": "2026-05-29",
      "corp_name": "휴마시스",
      "stock_code": "205470",
      "market": "KOSDAQ",
      "corp_code": "01042979",
      "repror": "인콘",
      "ofcps": "-",
      "rgist": "-",
      "main_shrholdr": "사실상지배주주",
      "irds_cnt": "144,585",
      "total_cnt": "1,748,849",
      "irds_rate": "0.59",
      "hold_rate": "7.09",
      "method": "장내매수"
    },
    {
      "rcept_no": "20260529001860",
      "rcept_dt": "2026-05-29",
      "corp_name": "한울반도체",
      "stock_code": "320000",
      "market": "KOSDAQ",
      "corp_code": "01359815",
      "repror": "김백산",
      "ofcps": "대표이사",
      "rgist": "등기임원",
      "main_shrholdr": "-",
      "irds_cnt": "4,040",
      "total_cnt": "4,040",
      "irds_rate": "0.06",
      "hold_rate": "0.06",
      "method": "장내매수"
    },
    {
      "rcept_no": "20260529001824",
      "rcept_dt": "2026-05-29",
      "corp_name": "한울반도체",
      "stock_code": "320000",
      "market": "KOSDAQ",
      "corp_code": "01359815",
      "repror": "김기원",
      "ofcps": "부회장",
      "rgist": "비등기임원",
      "main_shrholdr": "-",
      "irds_cnt": "4,500",
      "total_cnt": "4,500",
      "irds_rate": "0.07",
      "hold_rate": "0.07",
      "method": "장내매수"
    },
    {
      "rcept_no": "20260529001756",
      "rcept_dt": "2026-05-29",
      "corp_name": "SIMPAC",
      "stock_code": "009160",
      "market": "KOSPI",
      "corp_code": "00138260",
      "repror": "최민영",
      "ofcps": "상무이사",
      "rgist": "비등기임원",
      "main_shrholdr": "-",
      "irds_cnt": "88,971",
      "total_cnt": "6,160,071",
      "irds_rate": "0.13",
      "hold_rate": "9.42",
      "method": "장내매수"
    },
    {
      "rcept_no": "20260529001747",
      "rcept_dt": "2026-05-29",
      "corp_name": "블루엠텍",
      "stock_code": "439580",
      "market": "KOSDAQ",
      "corp_code": "01559637",
      "repror": "연제량",
      "ofcps": "사내이사",
      "rgist": "등기임원",
      "main_shrholdr": "사실상지배주주",
      "irds_cnt": "75,456",
      "total_cnt": "3,600,456",
      "irds_rate": "0.12",
      "hold_rate": "10.64",
      "method": "장내매수"
    },
    {
      "rcept_no": "20260529001731",
      "rcept_dt": "2026-05-29",
      "corp_name": "SK네트웍스",
      "stock_code": "001740",
      "market": "KOSPI",
      "corp_code": "00131780",
      "repror": "최신원",
      "ofcps": "임원",
      "rgist": "비등기임원",
      "main_shrholdr": "-",
      "irds_cnt": "6,000",
      "total_cnt": "128,000",
      "irds_rate": "0.00",
      "hold_rate": "0.06",
      "method": "장내매수"
    },
    {
      "rcept_no": "20260529001694",
      "rcept_dt": "2026-05-29",
      "corp_name": "남화산업",
      "stock_code": "111710",
      "market": "KOSDAQ",
      "corp_code": "00245694",
      "repror": "최현석",
      "ofcps": "상무이사",
      "rgist": "등기임원",
      "main_shrholdr": "-",
      "irds_cnt": "39,277",
      "total_cnt": "593,236",
      "irds_rate": "0.19",
      "hold_rate": "2.88",
      "method": "장내매수"
    },
    {
      "rcept_no": "20260529001627",
      "rcept_dt": "2026-05-29",
      "corp_name": "삼성전자",
      "stock_code": "005930",
      "market": "KOSPI",
      "corp_code": "00126380",
      "repror": "김경석",
      "ofcps": "상무",
      "rgist": "비등기임원",
      "main_shrholdr": "-",
      "irds_cnt": "1",
      "total_cnt": "237",
      "irds_rate": "0.00",
      "hold_rate": "0.00",
      "method": "장내매수"
    },
    {
      "rcept_no": "20260529001498",
      "rcept_dt": "2026-05-29",
      "corp_name": "사조오양",
      "stock_code": "006090",
      "market": "KOSPI",
      "corp_code": "00141875",
      "repror": "주지홍",
      "ofcps": "부 회 장",
      "rgist": "비등기임원",
      "main_shrholdr": "-",
      "irds_cnt": "28,983",
      "total_cnt": "85,722",
      "irds_rate": "0.31",
      "hold_rate": "0.91",
      "method": "장내매수"
    },
    {
      "rcept_no": "20260529001472",
      "rcept_dt": "2026-05-29",
      "corp_name": "유니크",
      "stock_code": "011320",
      "market": "KOSDAQ",
      "corp_code": "00147152",
      "repror": "안영구",
      "ofcps": "대표이사 회장",
      "rgist": "등기임원",
      "main_shrholdr": "사실상지배주주",
      "irds_cnt": "40,000",
      "total_cnt": "3,663,623",
      "irds_rate": "0.20",
      "hold_rate": "18.96",
      "method": "장내매수"
    },
    {
      "rcept_no": "20260529001448",
      "rcept_dt": "2026-05-29",
      "corp_name": "옵티팜",
      "stock_code": "153710",
      "market": "KOSDAQ",
      "corp_code": "00971726",
      "repror": "김현일",
      "ofcps": "대표이사",
      "rgist": "등기임원",
      "main_shrholdr": "-",
      "irds_cnt": "2,000",
      "total_cnt": "306,650",
      "irds_rate": "0.01",
      "hold_rate": "2.09",
      "method": "장내매수"
    },
    {
      "rcept_no": "20260529001235",
      "rcept_dt": "2026-05-29",
      "corp_name": "대성미생물",
      "stock_code": "036480",
      "market": "KOSDAQ",
      "corp_code": "00177320",
      "repror": "최승훈",
      "ofcps": "대표이사",
      "rgist": "등기임원",
      "main_shrholdr": "-",
      "irds_cnt": "3,500",
      "total_cnt": "33,873",
      "irds_rate": "0.09",
      "hold_rate": "0.89",
      "method": "장내매수"
    },
    {
      "rcept_no": "20260529001220",
      "rcept_dt": "2026-05-29",
      "corp_name": "대성미생물",
      "stock_code": "036480",
      "market": "KOSDAQ",
      "corp_code": "00177320",
      "repror": "최승훈",
      "ofcps": "대표이사",
      "rgist": "등기임원",
      "main_shrholdr": "-",
      "irds_cnt": "1,134",
      "total_cnt": "30,373",
      "irds_rate": "0.03",
      "hold_rate": "0.80",
      "method": "장내매수"
    },
    {
      "rcept_no": "20260529001126",
      "rcept_dt": "2026-05-29",
      "corp_name": "대성미생물",
      "stock_code": "036480",
      "market": "KOSDAQ",
      "corp_code": "00177320",
      "repror": "인실리코",
      "ofcps": "-",
      "rgist": "-",
      "main_shrholdr": "사실상지배주주",
      "irds_cnt": "9,086",
      "total_cnt": "1,475,826",
      "irds_rate": "0.24",
      "hold_rate": "38.84",
      "method": "장내매수"
    },
    {
      "rcept_no": "20260529001096",
      "rcept_dt": "2026-05-29",
      "corp_name": "일진전기",
      "stock_code": "103590",
      "market": "KOSPI",
      "corp_code": "00683469",
      "repror": "유상석",
      "ofcps": "대표이사",
      "rgist": "등기임원",
      "main_shrholdr": "-",
      "irds_cnt": "300",
      "total_cnt": "300",
      "irds_rate": "0.01",
      "hold_rate": "0.01",
      "method": "장내매수"
    },
    {
      "rcept_no": "20260529001008",
      "rcept_dt": "2026-05-29",
      "corp_name": "대성미생물",
      "stock_code": "036480",
      "market": "KOSDAQ",
      "corp_code": "00177320",
      "repror": "인실리코",
      "ofcps": "-",
      "rgist": "-",
      "main_shrholdr": "사실상지배주주",
      "irds_cnt": "1,466,740",
      "total_cnt": "1,466,740",
      "irds_rate": "38.6",
      "hold_rate": "38.6",
      "method": "장외매수"
    },
    {
      "rcept_no": "20260529000988",
      "rcept_dt": "2026-05-29",
      "corp_name": "DB증권",
      "stock_code": "016610",
      "market": "KOSPI",
      "corp_code": "00115694",
      "repror": "유승우",
      "ofcps": "상무보",
      "rgist": "비등기임원",
      "main_shrholdr": "-",
      "irds_cnt": "2,000",
      "total_cnt": "12,015",
      "irds_rate": "0.004",
      "hold_rate": "0.028",
      "method": "장내매수"
    },
    {
      "rcept_no": "20260529000951",
      "rcept_dt": "2026-05-29",
      "corp_name": "DB증권",
      "stock_code": "016610",
      "market": "KOSPI",
      "corp_code": "00115694",
      "repror": "류용동",
      "ofcps": "상무보",
      "rgist": "비등기임원",
      "main_shrholdr": "-",
      "irds_cnt": "100",
      "total_cnt": "4,249",
      "irds_rate": "0.000",
      "hold_rate": "0.010",
      "method": "장내매수"
    },
    {
      "rcept_no": "20260529000890",
      "rcept_dt": "2026-05-29",
      "corp_name": "하이트진로",
      "stock_code": "000080",
      "market": "KOSPI",
      "corp_code": "00150244",
      "repror": "신민철",
      "ofcps": "상무",
      "rgist": "비등기임원",
      "main_shrholdr": "-",
      "irds_cnt": "3,000",
      "total_cnt": "3,000",
      "irds_rate": "0.00",
      "hold_rate": "0.00",
      "method": "장내매수"
    },
    {
      "rcept_no": "20260529000788",
      "rcept_dt": "2026-05-29",
      "corp_name": "SM Life Design",
      "stock_code": "063440",
      "market": "KOSDAQ",
      "corp_code": "00367604",
      "repror": "남화민",
      "ofcps": "공동대표이사",
      "rgist": "등기임원",
      "main_shrholdr": "-",
      "irds_cnt": "69,854",
      "total_cnt": "300,000",
      "irds_rate": "0.16",
      "hold_rate": "0.66",
      "method": "장내매수"
    },
    {
      "rcept_no": "20260529000502",
      "rcept_dt": "2026-05-29",
      "corp_name": "케이옥션",
      "stock_code": "102370",
      "market": "KOSDAQ",
      "corp_code": "00668600",
      "repror": "티에이어드바이저",
      "ofcps": "-",
      "rgist": "-",
      "main_shrholdr": "10%이상주주",
      "irds_cnt": "91,226",
      "total_cnt": "13,670,538",
      "irds_rate": "0.34",
      "hold_rate": "50.21",
      "method": "장내매수"
    },
    {
      "rcept_no": "20260529000488",
      "rcept_dt": "2026-05-29",
      "corp_name": "오비고",
      "stock_code": "352910",
      "market": "KOSDAQ",
      "corp_code": "00494546",
      "repror": "장영준",
      "ofcps": "기타비상무이사",
      "rgist": "등기임원",
      "main_shrholdr": "10%이상주주",
      "irds_cnt": "82,009",
      "total_cnt": "2,794,163",
      "irds_rate": "0.65",
      "hold_rate": "22.11",
      "method": "장내매수"
    },
    {
      "rcept_no": "20260529000450",
      "rcept_dt": "2026-05-29",
      "corp_name": "신흥",
      "stock_code": "004080",
      "market": "KOSPI",
      "corp_code": "00173795",
      "repror": "서정인",
      "ofcps": "이사",
      "rgist": "비등기임원",
      "main_shrholdr": "-",
      "irds_cnt": "1,320",
      "total_cnt": "4,977",
      "irds_rate": "0.01",
      "hold_rate": "0.05",
      "method": "장외매수"
    },
    {
      "rcept_no": "20260529000433",
      "rcept_dt": "2026-05-29",
      "corp_name": "신흥",
      "stock_code": "004080",
      "market": "KOSPI",
      "corp_code": "00173795",
      "repror": "류정근",
      "ofcps": "이사",
      "rgist": "비등기임원",
      "main_shrholdr": "-",
      "irds_cnt": "1,040",
      "total_cnt": "4,190",
      "irds_rate": "0.01",
      "hold_rate": "0.04",
      "method": "시간외매매"
    },
    {
      "rcept_no": "20260529000421",
      "rcept_dt": "2026-05-29",
      "corp_name": "신흥",
      "stock_code": "004080",
      "market": "KOSPI",
      "corp_code": "00173795",
      "repror": "최천수",
      "ofcps": "전무",
      "rgist": "비등기임원",
      "main_shrholdr": "-",
      "irds_cnt": "1,780",
      "total_cnt": "35,594",
      "irds_rate": "0.02",
      "hold_rate": "0.38",
      "method": "시간외매매"
    },
    {
      "rcept_no": "20260529000291",
      "rcept_dt": "2026-05-29",
      "corp_name": "위세아이텍",
      "stock_code": "065370",
      "market": "KOSDAQ",
      "corp_code": "00374738",
      "repror": "이제동",
      "ofcps": "대표이사",
      "rgist": "등기임원",
      "main_shrholdr": "-",
      "irds_cnt": "2,333",
      "total_cnt": "87,000",
      "irds_rate": "0.03",
      "hold_rate": "1.18",
      "method": "장내매수"
    },
    {
      "rcept_no": "20260529000288",
      "rcept_dt": "2026-05-29",
      "corp_name": "우리엔터프라이즈",
      "stock_code": "037400",
      "market": "KOSDAQ",
      "corp_code": "00155692",
      "repror": "윤철주",
      "ofcps": "회장",
      "rgist": "비등기임원",
      "main_shrholdr": "사실상지배주주",
      "irds_cnt": "250,000",
      "total_cnt": "534,760",
      "irds_rate": "0.95",
      "hold_rate": "2.03",
      "method": "장내매수"
    },
    {
      "rcept_no": "20260529000261",
      "rcept_dt": "2026-05-29",
      "corp_name": "멀티캠퍼스",
      "stock_code": "067280",
      "market": "KOSDAQ",
      "corp_code": "00425351",
      "repror": "안재우",
      "ofcps": "대표이사",
      "rgist": "등기임원",
      "main_shrholdr": "-",
      "irds_cnt": "2,000",
      "total_cnt": "2,000",
      "irds_rate": "0.03",
      "hold_rate": "0.03",
      "method": "장내매수"
    },
    {
      "rcept_no": "20260529000103",
      "rcept_dt": "2026-05-29",
      "corp_name": "HLB바이오스텝",
      "stock_code": "278650",
      "market": "KOSDAQ",
      "corp_code": "01189438",
      "repror": "백성진",
      "ofcps": "대표이사",
      "rgist": "등기임원",
      "main_shrholdr": "-",
      "irds_cnt": "5,000",
      "total_cnt": "10,000",
      "irds_rate": "0.03",
      "hold_rate": "0.06",
      "method": "장내매수"
    },
    {
      "rcept_no": "20260529000062",
      "rcept_dt": "2026-05-29",
      "corp_name": "대한뉴팜",
      "stock_code": "054670",
      "market": "KOSDAQ",
      "corp_code": "00207375",
      "repror": "이원석",
      "ofcps": "대표이사",
      "rgist": "등기임원",
      "main_shrholdr": "-",
      "irds_cnt": "9,166",
      "total_cnt": "1,187,365",
      "irds_rate": "0.06",
      "hold_rate": "8.27",
      "method": "장내매수"
    },
    {
      "rcept_no": "20260529000043",
      "rcept_dt": "2026-05-29",
      "corp_name": "드림어스컴퍼니",
      "stock_code": "060570",
      "market": "KOSDAQ",
      "corp_code": "00364467",
      "repror": "이새롬",
      "ofcps": "성장사업그룹장",
      "rgist": "비등기임원",
      "main_shrholdr": "-",
      "irds_cnt": "10,000",
      "total_cnt": "10,000",
      "irds_rate": "0.01",
      "hold_rate": "0.01",
      "method": "장내매수"
    },
    {
      "rcept_no": "20260529000041",
      "rcept_dt": "2026-05-29",
      "corp_name": "바이오노트",
      "stock_code": "377740",
      "market": "KOSPI",
      "corp_code": "00622787",
      "repror": "박철세",
      "ofcps": "사외이사",
      "rgist": "등기임원",
      "main_shrholdr": "-",
      "irds_cnt": "1,950",
      "total_cnt": "7,950",
      "irds_rate": "0.01",
      "hold_rate": "0.01",
      "method": "장내매수"
    },
    {
      "rcept_no": "20260529000038",
      "rcept_dt": "2026-05-29",
      "corp_name": "평화산업",
      "stock_code": "090080",
      "market": "KOSPI",
      "corp_code": "00573579",
      "repror": "황순용",
      "ofcps": "부회장",
      "rgist": "등기임원",
      "main_shrholdr": "-",
      "irds_cnt": "50,000",
      "total_cnt": "50,000",
      "irds_rate": "0.09",
      "hold_rate": "0.09",
      "method": "장내매수"
    },
    {
      "rcept_no": "20260529000032",
      "rcept_dt": "2026-05-29",
      "corp_name": "프럼파스트",
      "stock_code": "035200",
      "market": "KOSDAQ",
      "corp_code": "00356389",
      "repror": "원연경",
      "ofcps": "이사",
      "rgist": "등기임원",
      "main_shrholdr": "-",
      "irds_cnt": "17,800",
      "total_cnt": "917,800",
      "irds_rate": "0.18",
      "hold_rate": "9.43",
      "method": "장내매수"
    },
    {
      "rcept_no": "20260528001021",
      "rcept_dt": "2026-05-28",
      "corp_name": "하림지주",
      "stock_code": "003380",
      "market": "KOSDAQ",
      "corp_code": "00148364",
      "repror": "한국바이오텍",
      "ofcps": "-",
      "rgist": "-",
      "main_shrholdr": "10%이상주주",
      "irds_cnt": "63,892",
      "total_cnt": "20,956,300",
      "irds_rate": "0.06",
      "hold_rate": "18.71",
      "method": "장내매수"
    },
    {
      "rcept_no": "20260528000963",
      "rcept_dt": "2026-05-28",
      "corp_name": "삼천리",
      "stock_code": "004690",
      "market": "KOSPI",
      "corp_code": "00128555",
      "repror": "이성근",
      "ofcps": "전무",
      "rgist": "비등기임원",
      "main_shrholdr": "-",
      "irds_cnt": "100",
      "total_cnt": "300",
      "irds_rate": "0.00",
      "hold_rate": "0.00",
      "method": "장내매수"
    },
    {
      "rcept_no": "20260528000807",
      "rcept_dt": "2026-05-28",
      "corp_name": "에이치엔에스하이텍",
      "stock_code": "044990",
      "market": "KOSDAQ",
      "corp_code": "00311216",
      "repror": "배의호",
      "ofcps": "부회장",
      "rgist": "비등기임원",
      "main_shrholdr": "-",
      "irds_cnt": "500",
      "total_cnt": "39,045",
      "irds_rate": "0.01",
      "hold_rate": "0.51",
      "method": "장내매수"
    },
    {
      "rcept_no": "20260528000770",
      "rcept_dt": "2026-05-28",
      "corp_name": "이리츠코크렙",
      "stock_code": "088260",
      "market": "KOSPI",
      "corp_code": "00544452",
      "repror": "미래에셋자산운용",
      "ofcps": "-",
      "rgist": "-",
      "main_shrholdr": "10%이상주주",
      "irds_cnt": "170,842",
      "total_cnt": "11,059,241",
      "irds_rate": "0.27",
      "hold_rate": "17.46",
      "method": "장내매수"
    },
    {
      "rcept_no": "20260528000768",
      "rcept_dt": "2026-05-28",
      "corp_name": "신한알파리츠",
      "stock_code": "293940",
      "market": "KOSPI",
      "corp_code": "01276594",
      "repror": "미래에셋자산운용",
      "ofcps": "-",
      "rgist": "-",
      "main_shrholdr": "10%이상주주",
      "irds_cnt": "440,710",
      "total_cnt": "22,924,606",
      "irds_rate": "0.37",
      "hold_rate": "18.96",
      "method": "장내매수"
    },
    {
      "rcept_no": "20260528000764",
      "rcept_dt": "2026-05-28",
      "corp_name": "롯데리츠",
      "stock_code": "330590",
      "market": "KOSPI",
      "corp_code": "01363818",
      "repror": "미래에셋자산운용",
      "ofcps": "-",
      "rgist": "-",
      "main_shrholdr": "10%이상주주",
      "irds_cnt": "777,669",
      "total_cnt": "38,878,907",
      "irds_rate": "0.26",
      "hold_rate": "13.45",
      "method": "장내매수"
    },
    {
      "rcept_no": "20260528000754",
      "rcept_dt": "2026-05-28",
      "corp_name": "HS효성첨단소재",
      "stock_code": "298050",
      "market": "KOSPI",
      "corp_code": "01316254",
      "repror": "HS효성",
      "ofcps": "-",
      "rgist": "-",
      "main_shrholdr": "10%이상주주",
      "irds_cnt": "4,273",
      "total_cnt": "1,343,986",
      "irds_rate": "0.09",
      "hold_rate": "30.00",
      "method": "장내매수"
    },
    {
      "rcept_no": "20260528000744",
      "rcept_dt": "2026-05-28",
      "corp_name": "대한약품",
      "stock_code": "023910",
      "market": "KOSDAQ",
      "corp_code": "00113128",
      "repror": "이윤우",
      "ofcps": "회장",
      "rgist": "등기임원",
      "main_shrholdr": "사실상지배주주",
      "irds_cnt": "1,000",
      "total_cnt": "1,480,404",
      "irds_rate": "0.01",
      "hold_rate": "24.67",
      "method": "장내매수"
    },
    {
      "rcept_no": "20260528000742",
      "rcept_dt": "2026-05-28",
      "corp_name": "SK리츠",
      "stock_code": "395400",
      "market": "KOSPI",
      "corp_code": "01535150",
      "repror": "미래에셋자산운용",
      "ofcps": "-",
      "rgist": "-",
      "main_shrholdr": "10%이상주주",
      "irds_cnt": "971,631",
      "total_cnt": "58,616,005",
      "irds_rate": "0.32",
      "hold_rate": "19.47",
      "method": "장내매수"
    },
    {
      "rcept_no": "20260528000738",
      "rcept_dt": "2026-05-28",
      "corp_name": "ESR켄달스퀘어리츠",
      "stock_code": "365550",
      "market": "KOSPI",
      "corp_code": "01437186",
      "repror": "미래에셋자산운용",
      "ofcps": "-",
      "rgist": "-",
      "main_shrholdr": "10%이상주주",
      "irds_cnt": "674,475",
      "total_cnt": "41,801,747",
      "irds_rate": "0.28",
      "hold_rate": "16.99",
      "method": "장내매수"
    },
    {
      "rcept_no": "20260528000734",
      "rcept_dt": "2026-05-28",
      "corp_name": "이지홀딩스",
      "stock_code": "035810",
      "market": "KOSDAQ",
      "corp_code": "00242378",
      "repror": "아날로그",
      "ofcps": "-",
      "rgist": "-",
      "main_shrholdr": "10%이상주주",
      "irds_cnt": "638,000",
      "total_cnt": "15,166,638",
      "irds_rate": "0.99",
      "hold_rate": "23.51",
      "method": "장내매수"
    },
    {
      "rcept_no": "20260528000732",
      "rcept_dt": "2026-05-28",
      "corp_name": "대교",
      "stock_code": "019680",
      "market": "KOSPI",
      "corp_code": "00108913",
      "repror": "대교홀딩스",
      "ofcps": "-",
      "rgist": "-",
      "main_shrholdr": "10%이상주주",
      "irds_cnt": "1,800,000",
      "total_cnt": "47,971,200",
      "irds_rate": "1.73",
      "hold_rate": "46.07",
      "method": "장외매수"
    },
    {
      "rcept_no": "20260528000707",
      "rcept_dt": "2026-05-28",
      "corp_name": "카카오",
      "stock_code": "035720",
      "market": "KOSPI",
      "corp_code": "00258801",
      "repror": "윤영진",
      "ofcps": "브랜드\n성과리더",
      "rgist": "비등기임원",
      "main_shrholdr": "-",
      "irds_cnt": "8",
      "total_cnt": "10,687",
      "irds_rate": "0.00",
      "hold_rate": "0.00",
      "method": "장내매수"
    },
    {
      "rcept_no": "20260528000685",
      "rcept_dt": "2026-05-28",
      "corp_name": "유안타증권",
      "stock_code": "003470",
      "market": "KOSPI",
      "corp_code": "00117601",
      "repror": "조우진",
      "ofcps": "상무보",
      "rgist": "비등기임원",
      "main_shrholdr": "-",
      "irds_cnt": "500",
      "total_cnt": "500",
      "irds_rate": "0.00",
      "hold_rate": "0.00",
      "method": "장내매수"
    },
    {
      "rcept_no": "20260528000665",
      "rcept_dt": "2026-05-28",
      "corp_name": "삼익악기",
      "stock_code": "002450",
      "market": "KOSPI",
      "corp_code": "00127857",
      "repror": "재단법인 삼익문화재단",
      "ofcps": "-",
      "rgist": "-",
      "main_shrholdr": "사실상지배주주",
      "irds_cnt": "1,570,060",
      "total_cnt": "3,940,060",
      "irds_rate": "1.73",
      "hold_rate": "4.35",
      "method": "장내매수"
    },
    {
      "rcept_no": "20260528000654",
      "rcept_dt": "2026-05-28",
      "corp_name": "코웨이",
      "stock_code": "021240",
      "market": "KOSPI",
      "corp_code": "00170558",
      "repror": "방준혁",
      "ofcps": "이사회 의장",
      "rgist": "등기임원",
      "main_shrholdr": "-",
      "irds_cnt": "34,000",
      "total_cnt": "76,000",
      "irds_rate": "0.05",
      "hold_rate": "0.11",
      "method": "장내매수"
    },
    {
      "rcept_no": "20260528000618",
      "rcept_dt": "2026-05-28",
      "corp_name": "미원상사",
      "stock_code": "002840",
      "market": "KOSPI",
      "corp_code": "00121932",
      "repror": "가제순",
      "ofcps": "전무",
      "rgist": "등기임원",
      "main_shrholdr": "-",
      "irds_cnt": "450",
      "total_cnt": "3,000",
      "irds_rate": "0.01",
      "hold_rate": "0.06",
      "method": "장내매수"
    },
    {
      "rcept_no": "20260528000614",
      "rcept_dt": "2026-05-28",
      "corp_name": "코웨이",
      "stock_code": "021240",
      "market": "KOSPI",
      "corp_code": "00170558",
      "repror": "넷마블",
      "ofcps": "-",
      "rgist": "-",
      "main_shrholdr": "10%이상주주",
      "irds_cnt": "145,000",
      "total_cnt": "18,824,446",
      "irds_rate": "0.20",
      "hold_rate": "26.60",
      "method": "장내매수"
    },
    {
      "rcept_no": "20260528000589",
      "rcept_dt": "2026-05-28",
      "corp_name": "삼영에스앤씨",
      "stock_code": "361670",
      "market": "KOSDAQ",
      "corp_code": "00405506",
      "repror": "고승남",
      "ofcps": "전무이사",
      "rgist": "비등기임원",
      "main_shrholdr": "-",
      "irds_cnt": "1,831",
      "total_cnt": "11,563",
      "irds_rate": "0.03",
      "hold_rate": "0.20",
      "method": "장내매수"
    },
    {
      "rcept_no": "20260528000569",
      "rcept_dt": "2026-05-28",
      "corp_name": "삼영에스앤씨",
      "stock_code": "361670",
      "market": "KOSDAQ",
      "corp_code": "00405506",
      "repror": "박상익",
      "ofcps": "대표이사",
      "rgist": "등기임원",
      "main_shrholdr": "-",
      "irds_cnt": "6,000",
      "total_cnt": "111,000",
      "irds_rate": "0.11",
      "hold_rate": "1.96",
      "method": "장내매수"
    },
    {
      "rcept_no": "20260528000482",
      "rcept_dt": "2026-05-28",
      "corp_name": "금호에이치티",
      "stock_code": "214330",
      "market": "KOSPI",
      "corp_code": "00105606",
      "repror": "김두인",
      "ofcps": "대표이사",
      "rgist": "등기임원",
      "main_shrholdr": "-",
      "irds_cnt": "20,000",
      "total_cnt": "60,000",
      "irds_rate": "0.11",
      "hold_rate": "0.29",
      "method": "장내매수"
    },
    {
      "rcept_no": "20260528000407",
      "rcept_dt": "2026-05-28",
      "corp_name": "아진전자부품",
      "stock_code": "009320",
      "market": "KOSPI",
      "corp_code": "00111689",
      "repror": "이석호",
      "ofcps": "상무이사",
      "rgist": "비등기임원",
      "main_shrholdr": "-",
      "irds_cnt": "20,401",
      "total_cnt": "20,401",
      "irds_rate": "0.04",
      "hold_rate": "0.04",
      "method": "장내매수"
    },
    {
      "rcept_no": "20260528000394",
      "rcept_dt": "2026-05-28",
      "corp_name": "그리드위즈",
      "stock_code": "453450",
      "market": "KOSDAQ",
      "corp_code": "01299203",
      "repror": "류준우",
      "ofcps": "사장",
      "rgist": "등기임원",
      "main_shrholdr": "-",
      "irds_cnt": "4,700",
      "total_cnt": "342,200",
      "irds_rate": "0.06",
      "hold_rate": "4.31",
      "method": "장내매수"
    },
    {
      "rcept_no": "20260528000376",
      "rcept_dt": "2026-05-28",
      "corp_name": "에스켐",
      "stock_code": "475660",
      "market": "KOSDAQ",
      "corp_code": "01383779",
      "repror": "이대원",
      "ofcps": "사내이사 (부사장)",
      "rgist": "등기임원",
      "main_shrholdr": "-",
      "irds_cnt": "1,500",
      "total_cnt": "26,000",
      "irds_rate": "0.02",
      "hold_rate": "0.33",
      "method": "장내매수"
    },
    {
      "rcept_no": "20260528000299",
      "rcept_dt": "2026-05-28",
      "corp_name": "삼성에스디에스",
      "stock_code": "018260",
      "market": "KOSPI",
      "corp_code": "00126186",
      "repror": "민대홍",
      "ofcps": "상무",
      "rgist": "비등기임원",
      "main_shrholdr": "-",
      "irds_cnt": "100",
      "total_cnt": "100",
      "irds_rate": "0.00",
      "hold_rate": "0.00",
      "method": "장내매수"
    },
    {
      "rcept_no": "20260528000293",
      "rcept_dt": "2026-05-28",
      "corp_name": "BNK금융지주",
      "stock_code": "138930",
      "market": "KOSPI",
      "corp_code": "00858364",
      "repror": "김태호",
      "ofcps": "상무",
      "rgist": "비등기임원",
      "main_shrholdr": "-",
      "irds_cnt": "2,000",
      "total_cnt": "2,000",
      "irds_rate": "0.00",
      "hold_rate": "0.00",
      "method": "장내매수"
    },
    {
      "rcept_no": "20260528000292",
      "rcept_dt": "2026-05-28",
      "corp_name": "대화제약",
      "stock_code": "067080",
      "market": "KOSDAQ",
      "corp_code": "00210740",
      "repror": "방신원",
      "ofcps": "상무",
      "rgist": "비등기임원",
      "main_shrholdr": "-",
      "irds_cnt": "1,000",
      "total_cnt": "7,000",
      "irds_rate": "0.01",
      "hold_rate": "0.04",
      "method": "장내매수"
    },
    {
      "rcept_no": "20260528000290",
      "rcept_dt": "2026-05-28",
      "corp_name": "BNK금융지주",
      "stock_code": "138930",
      "market": "KOSPI",
      "corp_code": "00858364",
      "repror": "이광준",
      "ofcps": "상무",
      "rgist": "비등기임원",
      "main_shrholdr": "-",
      "irds_cnt": "2,000",
      "total_cnt": "4,000",
      "irds_rate": "0.00",
      "hold_rate": "0.00",
      "method": "장내매수"
    },
    {
      "rcept_no": "20260528000288",
      "rcept_dt": "2026-05-28",
      "corp_name": "BNK금융지주",
      "stock_code": "138930",
      "market": "KOSPI",
      "corp_code": "00858364",
      "repror": "이동렬",
      "ofcps": "전무",
      "rgist": "비등기임원",
      "main_shrholdr": "-",
      "irds_cnt": "2,500",
      "total_cnt": "2,500",
      "irds_rate": "0.00",
      "hold_rate": "0.00",
      "method": "장내매수"
    },
    {
      "rcept_no": "20260528000285",
      "rcept_dt": "2026-05-28",
      "corp_name": "BNK금융지주",
      "stock_code": "138930",
      "market": "KOSPI",
      "corp_code": "00858364",
      "repror": "김주성",
      "ofcps": "전무",
      "rgist": "비등기임원",
      "main_shrholdr": "-",
      "irds_cnt": "3,000",
      "total_cnt": "3,000",
      "irds_rate": "0.00",
      "hold_rate": "0.00",
      "method": "장내매수"
    },
    {
      "rcept_no": "20260528000284",
      "rcept_dt": "2026-05-28",
      "corp_name": "BNK금융지주",
      "stock_code": "138930",
      "market": "KOSPI",
      "corp_code": "00858364",
      "repror": "이한창",
      "ofcps": "전무",
      "rgist": "비등기임원",
      "main_shrholdr": "-",
      "irds_cnt": "3,500",
      "total_cnt": "23,500",
      "irds_rate": "0.00",
      "hold_rate": "0.01",
      "method": "장내매수"
    },
    {
      "rcept_no": "20260528000282",
      "rcept_dt": "2026-05-28",
      "corp_name": "대화제약",
      "stock_code": "067080",
      "market": "KOSDAQ",
      "corp_code": "00210740",
      "repror": "김은석",
      "ofcps": "대표이사",
      "rgist": "등기임원",
      "main_shrholdr": "-",
      "irds_cnt": "2,319",
      "total_cnt": "213,069",
      "irds_rate": "0.01",
      "hold_rate": "1.14",
      "method": "장내매수"
    },
    {
      "rcept_no": "20260528000281",
      "rcept_dt": "2026-05-28",
      "corp_name": "BNK금융지주",
      "stock_code": "138930",
      "market": "KOSPI",
      "corp_code": "00858364",
      "repror": "홍명종",
      "ofcps": "부사장",
      "rgist": "비등기임원",
      "main_shrholdr": "-",
      "irds_cnt": "3,000",
      "total_cnt": "3,000",
      "irds_rate": "0.00",
      "hold_rate": "0.00",
      "method": "장내매수"
    },
    {
      "rcept_no": "20260528000274",
      "rcept_dt": "2026-05-28",
      "corp_name": "BNK금융지주",
      "stock_code": "138930",
      "market": "KOSPI",
      "corp_code": "00858364",
      "repror": "박성욱",
      "ofcps": "부사장",
      "rgist": "비등기임원",
      "main_shrholdr": "-",
      "irds_cnt": "3,000",
      "total_cnt": "23,000",
      "irds_rate": "0.00",
      "hold_rate": "0.01",
      "method": "장내매수"
    },
    {
      "rcept_no": "20260528000266",
      "rcept_dt": "2026-05-28",
      "corp_name": "BNK금융지주",
      "stock_code": "138930",
      "market": "KOSPI",
      "corp_code": "00858364",
      "repror": "강종훈",
      "ofcps": "부사장",
      "rgist": "비등기임원",
      "main_shrholdr": "-",
      "irds_cnt": "3,000",
      "total_cnt": "30,307",
      "irds_rate": "0.00",
      "hold_rate": "0.01",
      "method": "장내매수"
    },
    {
      "rcept_no": "20260528000239",
      "rcept_dt": "2026-05-28",
      "corp_name": "BNK금융지주",
      "stock_code": "138930",
      "market": "KOSPI",
      "corp_code": "00858364",
      "repror": "빈대인",
      "ofcps": "회 장",
      "rgist": "등기임원",
      "main_shrholdr": "-",
      "irds_cnt": "5,000",
      "total_cnt": "66,885",
      "irds_rate": "0.00",
      "hold_rate": "0.02",
      "method": "장내매수"
    },
    {
      "rcept_no": "20260528000209",
      "rcept_dt": "2026-05-28",
      "corp_name": "일양약품",
      "stock_code": "007570",
      "market": "KOSPI",
      "corp_code": "00146454",
      "repror": "정연찬",
      "ofcps": "상무이사",
      "rgist": "비등기임원",
      "main_shrholdr": "-",
      "irds_cnt": "1,050",
      "total_cnt": "1,120",
      "irds_rate": "0.00",
      "hold_rate": "0.01",
      "method": "장내매수"
    },
    {
      "rcept_no": "20260528000202",
      "rcept_dt": "2026-05-28",
      "corp_name": "일양약품",
      "stock_code": "007570",
      "market": "KOSPI",
      "corp_code": "00146454",
      "repror": "송화준",
      "ofcps": "이사",
      "rgist": "비등기임원",
      "main_shrholdr": "-",
      "irds_cnt": "2,030",
      "total_cnt": "2,090",
      "irds_rate": "0.00",
      "hold_rate": "0.01",
      "method": "장내매수"
    },
    {
      "rcept_no": "20260528000160",
      "rcept_dt": "2026-05-28",
      "corp_name": "KT밀리의서재",
      "stock_code": "418470",
      "market": "KOSDAQ",
      "corp_code": "01467451",
      "repror": "정재욱",
      "ofcps": "대표이사",
      "rgist": "등기임원",
      "main_shrholdr": "-",
      "irds_cnt": "10,000",
      "total_cnt": "10,000",
      "irds_rate": "0.12",
      "hold_rate": "0.12",
      "method": "장내매수"
    },
    {
      "rcept_no": "20260528000134",
      "rcept_dt": "2026-05-28",
      "corp_name": "모두투어",
      "stock_code": "080160",
      "market": "KOSDAQ",
      "corp_code": "00456218",
      "repror": "최성민",
      "ofcps": "상무",
      "rgist": "등기임원",
      "main_shrholdr": "-",
      "irds_cnt": "1,400",
      "total_cnt": "5,260",
      "irds_rate": "0.01",
      "hold_rate": "0.03",
      "method": "장내매수"
    },
    {
      "rcept_no": "20260528000129",
      "rcept_dt": "2026-05-28",
      "corp_name": "모두투어",
      "stock_code": "080160",
      "market": "KOSDAQ",
      "corp_code": "00456218",
      "repror": "이철용",
      "ofcps": "이사",
      "rgist": "비등기임원",
      "main_shrholdr": "-",
      "irds_cnt": "650",
      "total_cnt": "5,406",
      "irds_rate": "0.00",
      "hold_rate": "0.03",
      "method": "장내매수"
    },
    {
      "rcept_no": "20260528000121",
      "rcept_dt": "2026-05-28",
      "corp_name": "모두투어",
      "stock_code": "080160",
      "market": "KOSDAQ",
      "corp_code": "00456218",
      "repror": "이우연",
      "ofcps": "이사",
      "rgist": "비등기임원",
      "main_shrholdr": "-",
      "irds_cnt": "500",
      "total_cnt": "2,610",
      "irds_rate": "0.00",
      "hold_rate": "0.01",
      "method": "장내매수"
    },
    {
      "rcept_no": "20260528000112",
      "rcept_dt": "2026-05-28",
      "corp_name": "모두투어",
      "stock_code": "080160",
      "market": "KOSDAQ",
      "corp_code": "00456218",
      "repror": "염경수",
      "ofcps": "상무",
      "rgist": "비등기임원",
      "main_shrholdr": "-",
      "irds_cnt": "1,000",
      "total_cnt": "8,067",
      "irds_rate": "0.00",
      "hold_rate": "0.04",
      "method": "장내매수"
    },
    {
      "rcept_no": "20260528000040",
      "rcept_dt": "2026-05-28",
      "corp_name": "코렌텍",
      "stock_code": "104540",
      "market": "KOSDAQ",
      "corp_code": "00541437",
      "repror": "박형철",
      "ofcps": "부사장",
      "rgist": "비등기임원",
      "main_shrholdr": "-",
      "irds_cnt": "2,000",
      "total_cnt": "2,000",
      "irds_rate": "0.01",
      "hold_rate": "0.01",
      "method": "장내매수"
    },
    {
      "rcept_no": "20260527000507",
      "rcept_dt": "2026-05-27",
      "corp_name": "영풍",
      "stock_code": "000670",
      "market": "KOSPI",
      "corp_code": "00141307",
      "repror": "강성두",
      "ofcps": "사장",
      "rgist": "비등기임원",
      "main_shrholdr": "-",
      "irds_cnt": "652",
      "total_cnt": "3,400",
      "irds_rate": "0.01",
      "hold_rate": "0.02",
      "method": "장내매수"
    },
    {
      "rcept_no": "20260527000495",
      "rcept_dt": "2026-05-27",
      "corp_name": "영풍",
      "stock_code": "000670",
      "market": "KOSPI",
      "corp_code": "00141307",
      "repror": "김기호",
      "ofcps": "대표이사 사장",
      "rgist": "등기임원",
      "main_shrholdr": "-",
      "irds_cnt": "1,125",
      "total_cnt": "1,125",
      "irds_rate": "0.01",
      "hold_rate": "0.01",
      "method": "장내매수"
    },
    {
      "rcept_no": "20260527000490",
      "rcept_dt": "2026-05-27",
      "corp_name": "우진",
      "stock_code": "105840",
      "market": "KOSPI",
      "corp_code": "00173944",
      "repror": "조재성",
      "ofcps": "상무이사",
      "rgist": "등기임원",
      "main_shrholdr": "-",
      "irds_cnt": "321",
      "total_cnt": "5,000",
      "irds_rate": "0.00",
      "hold_rate": "0.02",
      "method": "장내매수"
    },
    {
      "rcept_no": "20260527000480",
      "rcept_dt": "2026-05-27",
      "corp_name": "슈피겐코리아",
      "stock_code": "192440",
      "market": "KOSDAQ",
      "corp_code": "00917861",
      "repror": "김대영",
      "ofcps": "대표이사",
      "rgist": "등기임원",
      "main_shrholdr": "사실상지배주주",
      "irds_cnt": "6,265",
      "total_cnt": "2,511,472",
      "irds_rate": "0.10",
      "hold_rate": "40.40",
      "method": "장내매수"
    },
    {
      "rcept_no": "20260527000465",
      "rcept_dt": "2026-05-27",
      "corp_name": "SIMPAC",
      "stock_code": "009160",
      "market": "KOSPI",
      "corp_code": "00138260",
      "repror": "최민찬",
      "ofcps": "부사장",
      "rgist": "비등기임원",
      "main_shrholdr": "10%이상주주",
      "irds_cnt": "42,360",
      "total_cnt": "14,237,208",
      "irds_rate": "0.07",
      "hold_rate": "21.78",
      "method": "장내매수"
    },
    {
      "rcept_no": "20260527000455",
      "rcept_dt": "2026-05-27",
      "corp_name": "유안타증권",
      "stock_code": "003470",
      "market": "KOSPI",
      "corp_code": "00117601",
      "repror": "유태인",
      "ofcps": "상무보",
      "rgist": "비등기임원",
      "main_shrholdr": "-",
      "irds_cnt": "200",
      "total_cnt": "600",
      "irds_rate": "0.00",
      "hold_rate": "0.00",
      "method": "장내매수"
    },
    {
      "rcept_no": "20260527000450",
      "rcept_dt": "2026-05-27",
      "corp_name": "원익큐브",
      "stock_code": "014190",
      "market": "KOSDAQ",
      "corp_code": "00128175",
      "repror": "양지용",
      "ofcps": "전무",
      "rgist": "비등기임원",
      "main_shrholdr": "-",
      "irds_cnt": "17,000",
      "total_cnt": "17,000",
      "irds_rate": "0.05",
      "hold_rate": "0.05",
      "method": "장내매수"
    },
    {
      "rcept_no": "20260527000449",
      "rcept_dt": "2026-05-27",
      "corp_name": "에이치시티",
      "stock_code": "072990",
      "market": "KOSDAQ",
      "corp_code": "00527464",
      "repror": "정연춘",
      "ofcps": "이사",
      "rgist": "등기임원",
      "main_shrholdr": "-",
      "irds_cnt": "1,150",
      "total_cnt": "2,185",
      "irds_rate": "0.01",
      "hold_rate": "0.02",
      "method": "장내매수"
    },
    {
      "rcept_no": "20260527000442",
      "rcept_dt": "2026-05-27",
      "corp_name": "엠에프씨",
      "stock_code": "432980",
      "market": "KOSDAQ",
      "corp_code": "01217795",
      "repror": "홍문기",
      "ofcps": "부사장",
      "rgist": "비등기임원",
      "main_shrholdr": "-",
      "irds_cnt": "456",
      "total_cnt": "2,912",
      "irds_rate": "0.0",
      "hold_rate": "0.03",
      "method": "장내매수"
    },
    {
      "rcept_no": "20260527000435",
      "rcept_dt": "2026-05-27",
      "corp_name": "웰크론한텍",
      "stock_code": "076080",
      "market": "KOSDAQ",
      "corp_code": "00487546",
      "repror": "웰크론",
      "ofcps": "-",
      "rgist": "-",
      "main_shrholdr": "10%이상주주",
      "irds_cnt": "13,123",
      "total_cnt": "5,929,532",
      "irds_rate": "0.05",
      "hold_rate": "26.24",
      "method": "장내매수"
    },
    {
      "rcept_no": "20260527000430",
      "rcept_dt": "2026-05-27",
      "corp_name": "SCL사이언스",
      "stock_code": "246960",
      "market": "KOSDAQ",
      "corp_code": "01110182",
      "repror": "양춘식",
      "ofcps": "부사장",
      "rgist": "등기임원",
      "main_shrholdr": "-",
      "irds_cnt": "5,793",
      "total_cnt": "23,993",
      "irds_rate": "0.02",
      "hold_rate": "0.07",
      "method": "장내매수"
    },
    {
      "rcept_no": "20260527000427",
      "rcept_dt": "2026-05-27",
      "corp_name": "웰크론한텍",
      "stock_code": "076080",
      "market": "KOSDAQ",
      "corp_code": "00487546",
      "repror": "정성식",
      "ofcps": "부사장",
      "rgist": "등기임원",
      "main_shrholdr": "-",
      "irds_cnt": "5,000",
      "total_cnt": "217,419",
      "irds_rate": "0.02",
      "hold_rate": "0.96",
      "method": "장내매수"
    },
    {
      "rcept_no": "20260527000424",
      "rcept_dt": "2026-05-27",
      "corp_name": "에이루트",
      "stock_code": "096690",
      "market": "KOSDAQ",
      "corp_code": "00608839",
      "repror": "서문동군",
      "ofcps": "대표이사",
      "rgist": "등기임원",
      "main_shrholdr": "-",
      "irds_cnt": "3,003",
      "total_cnt": "73,059",
      "irds_rate": "0.08",
      "hold_rate": "1.82",
      "method": "장내매수"
    },
    {
      "rcept_no": "20260527000421",
      "rcept_dt": "2026-05-27",
      "corp_name": "에이루트",
      "stock_code": "096690",
      "market": "KOSDAQ",
      "corp_code": "00608839",
      "repror": "이대성",
      "ofcps": "사내이사",
      "rgist": "등기임원",
      "main_shrholdr": "-",
      "irds_cnt": "1,145",
      "total_cnt": "41,529",
      "irds_rate": "0.03",
      "hold_rate": "1.03",
      "method": "장내매수"
    },
    {
      "rcept_no": "20260527000418",
      "rcept_dt": "2026-05-27",
      "corp_name": "HL홀딩스",
      "stock_code": "060980",
      "market": "KOSPI",
      "corp_code": "00299002",
      "repror": "정지연",
      "ofcps": "상무",
      "rgist": "비등기임원",
      "main_shrholdr": "-",
      "irds_cnt": "6,800",
      "total_cnt": "217,940",
      "irds_rate": "0.07",
      "hold_rate": "2.40",
      "method": "장내매수"
    },
    {
      "rcept_no": "20260527000377",
      "rcept_dt": "2026-05-27",
      "corp_name": "미트박스",
      "stock_code": "475460",
      "market": "KOSDAQ",
      "corp_code": "01374717",
      "repror": "오세흥",
      "ofcps": "상무이사",
      "rgist": "비등기임원",
      "main_shrholdr": "-",
      "irds_cnt": "7,943",
      "total_cnt": "7,943",
      "irds_rate": "0.14",
      "hold_rate": "0.14",
      "method": "장내매수"
    },
    {
      "rcept_no": "20260527000366",
      "rcept_dt": "2026-05-27",
      "corp_name": "그래디언트",
      "stock_code": "035080",
      "market": "KOSDAQ",
      "corp_code": "00244561",
      "repror": "남인봉",
      "ofcps": "대표이사",
      "rgist": "등기임원",
      "main_shrholdr": "-",
      "irds_cnt": "2,657",
      "total_cnt": "29,657",
      "irds_rate": "0.02",
      "hold_rate": "0.26",
      "method": "장내매수"
    },
    {
      "rcept_no": "20260527000362",
      "rcept_dt": "2026-05-27",
      "corp_name": "한빛소프트",
      "stock_code": "047080",
      "market": "KOSDAQ",
      "corp_code": "00348292",
      "repror": "원지훈",
      "ofcps": "대표이사",
      "rgist": "등기임원",
      "main_shrholdr": "-",
      "irds_cnt": "8,000",
      "total_cnt": "30,000",
      "irds_rate": "0.03",
      "hold_rate": "0.12",
      "method": "장내매수"
    },
    {
      "rcept_no": "20260527000354",
      "rcept_dt": "2026-05-27",
      "corp_name": "동국산업",
      "stock_code": "005160",
      "market": "KOSDAQ",
      "corp_code": "00172680",
      "repror": "장효근",
      "ofcps": "이사",
      "rgist": "비등기임원",
      "main_shrholdr": "-",
      "irds_cnt": "3,500",
      "total_cnt": "10,300",
      "irds_rate": "0.01",
      "hold_rate": "0.02",
      "method": "장내매수"
    },
    {
      "rcept_no": "20260527000339",
      "rcept_dt": "2026-05-27",
      "corp_name": "이퓨쳐",
      "stock_code": "134060",
      "market": "KOSDAQ",
      "corp_code": "00788737",
      "repror": "이기현",
      "ofcps": "대표이사",
      "rgist": "등기임원",
      "main_shrholdr": "사실상지배주주",
      "irds_cnt": "2,332",
      "total_cnt": "1,200,698",
      "irds_rate": "0.05",
      "hold_rate": "25.18",
      "method": "장내매수"
    },
    {
      "rcept_no": "20260527000328",
      "rcept_dt": "2026-05-27",
      "corp_name": "비큐AI",
      "stock_code": "148780",
      "market": "KOSDAQ",
      "corp_code": "00980043",
      "repror": "임경환",
      "ofcps": "대표이사",
      "rgist": "등기임원",
      "main_shrholdr": "10%이상주주",
      "irds_cnt": "100,000",
      "total_cnt": "9,700,445",
      "irds_rate": "0.32",
      "hold_rate": "30.85",
      "method": "장내매수"
    },
    {
      "rcept_no": "20260527000301",
      "rcept_dt": "2026-05-27",
      "corp_name": "티비씨",
      "stock_code": "033830",
      "market": "KOSDAQ",
      "corp_code": "00204642",
      "repror": "김실화",
      "ofcps": "이사",
      "rgist": "등기임원",
      "main_shrholdr": "-",
      "irds_cnt": "11,950",
      "total_cnt": "12,000",
      "irds_rate": "0.01",
      "hold_rate": "0.01",
      "method": "장내매수"
    },
    {
      "rcept_no": "20260527000246",
      "rcept_dt": "2026-05-27",
      "corp_name": "티비씨",
      "stock_code": "033830",
      "market": "KOSDAQ",
      "corp_code": "00204642",
      "repror": "서명욱",
      "ofcps": "이사",
      "rgist": "등기임원",
      "main_shrholdr": "-",
      "irds_cnt": "16,000",
      "total_cnt": "16,000",
      "irds_rate": "0.02",
      "hold_rate": "0.02",
      "method": "장내매수"
    },
    {
      "rcept_no": "20260527000232",
      "rcept_dt": "2026-05-27",
      "corp_name": "유한양행",
      "stock_code": "000100",
      "market": "KOSPI",
      "corp_code": "00145109",
      "repror": "윤동수",
      "ofcps": "상무",
      "rgist": "비등기임원",
      "main_shrholdr": "-",
      "irds_cnt": "100",
      "total_cnt": "200",
      "irds_rate": "0.00",
      "hold_rate": "0.00",
      "method": "장내매수"
    },
    {
      "rcept_no": "20260527000228",
      "rcept_dt": "2026-05-27",
      "corp_name": "인터지스",
      "stock_code": "129260",
      "market": "KOSPI",
      "corp_code": "00151368",
      "repror": "최우일",
      "ofcps": "부사장",
      "rgist": "등기임원",
      "main_shrholdr": "-",
      "irds_cnt": "10,000",
      "total_cnt": "10,000",
      "irds_rate": "0.03",
      "hold_rate": "0.03",
      "method": "장내매수"
    },
    {
      "rcept_no": "20260527000224",
      "rcept_dt": "2026-05-27",
      "corp_name": "엠에프씨",
      "stock_code": "432980",
      "market": "KOSDAQ",
      "corp_code": "01217795",
      "repror": "이인배",
      "ofcps": "상무이사",
      "rgist": "비등기임원",
      "main_shrholdr": "-",
      "irds_cnt": "3,559",
      "total_cnt": "11,336",
      "irds_rate": "0.04",
      "hold_rate": "0.13",
      "method": "장내매수"
    },
    {
      "rcept_no": "20260527000213",
      "rcept_dt": "2026-05-27",
      "corp_name": "대동스틸",
      "stock_code": "048470",
      "market": "KOSDAQ",
      "corp_code": "00109268",
      "repror": "임지현",
      "ofcps": "전무이사",
      "rgist": "등기임원",
      "main_shrholdr": "-",
      "irds_cnt": "49,431",
      "total_cnt": "429,623",
      "irds_rate": "0.51",
      "hold_rate": "4.45",
      "method": "장내매수"
    },
    {
      "rcept_no": "20260527000206",
      "rcept_dt": "2026-05-27",
      "corp_name": "대동스틸",
      "stock_code": "048470",
      "market": "KOSDAQ",
      "corp_code": "00109268",
      "repror": "임주희",
      "ofcps": "대표이사",
      "rgist": "등기임원",
      "main_shrholdr": "-",
      "irds_cnt": "46,680",
      "total_cnt": "524,618",
      "irds_rate": "0.65",
      "hold_rate": "5.43",
      "method": "장내매수"
    },
    {
      "rcept_no": "20260527000194",
      "rcept_dt": "2026-05-27",
      "corp_name": "케이옥션",
      "stock_code": "102370",
      "market": "KOSDAQ",
      "corp_code": "00668600",
      "repror": "도현순",
      "ofcps": "대표이사",
      "rgist": "등기임원",
      "main_shrholdr": "사실상지배주주",
      "irds_cnt": "17,751",
      "total_cnt": "197,751",
      "irds_rate": "0.07",
      "hold_rate": "0.73",
      "method": "장내매수"
    },
    {
      "rcept_no": "20260527000163",
      "rcept_dt": "2026-05-27",
      "corp_name": "국제약품",
      "stock_code": "002720",
      "market": "KOSPI",
      "corp_code": "00104722",
      "repror": "최해성",
      "ofcps": "상무",
      "rgist": "비등기임원",
      "main_shrholdr": "-",
      "irds_cnt": "2,521",
      "total_cnt": "2,521",
      "irds_rate": "0.01",
      "hold_rate": "0.01",
      "method": "장내매수"
    },
    {
      "rcept_no": "20260527000162",
      "rcept_dt": "2026-05-27",
      "corp_name": "코리아나",
      "stock_code": "027050",
      "market": "KOSDAQ",
      "corp_code": "00152589",
      "repror": "김영태",
      "ofcps": "상무",
      "rgist": "비등기임원",
      "main_shrholdr": "-",
      "irds_cnt": "67,800",
      "total_cnt": "100,000",
      "irds_rate": "0.17",
      "hold_rate": "0.25",
      "method": "장내매수"
    },
    {
      "rcept_no": "20260527000141",
      "rcept_dt": "2026-05-27",
      "corp_name": "삼성에스디에스",
      "stock_code": "018260",
      "market": "KOSPI",
      "corp_code": "00126186",
      "repror": "김민",
      "ofcps": "상무",
      "rgist": "비등기임원",
      "main_shrholdr": "-",
      "irds_cnt": "100",
      "total_cnt": "100",
      "irds_rate": "0.00",
      "hold_rate": "0.00",
      "method": "장내매수"
    },
    {
      "rcept_no": "20260527000124",
      "rcept_dt": "2026-05-27",
      "corp_name": "TS트릴리온",
      "stock_code": "317240",
      "market": "KOSDAQ",
      "corp_code": "01353024",
      "repror": "김용주",
      "ofcps": "사내이사",
      "rgist": "등기임원",
      "main_shrholdr": "-",
      "irds_cnt": "143,000",
      "total_cnt": "600,000",
      "irds_rate": "0.49",
      "hold_rate": "2.06",
      "method": "장내매수"
    },
    {
      "rcept_no": "20260527000109",
      "rcept_dt": "2026-05-27",
      "corp_name": "한국토지신탁",
      "stock_code": "034830",
      "market": "KOSPI",
      "corp_code": "00233653",
      "repror": "이제혁",
      "ofcps": "상무",
      "rgist": "비등기임원",
      "main_shrholdr": "-",
      "irds_cnt": "94,263",
      "total_cnt": "172,633",
      "irds_rate": "0.04",
      "hold_rate": "0.07",
      "method": "장내매수"
    },
    {
      "rcept_no": "20260527000070",
      "rcept_dt": "2026-05-27",
      "corp_name": "케어젠",
      "stock_code": "214370",
      "market": "KOSDAQ",
      "corp_code": "00549891",
      "repror": "정용지",
      "ofcps": "대표이사",
      "rgist": "등기임원",
      "main_shrholdr": "10%이상주주",
      "irds_cnt": "2,223",
      "total_cnt": "33,998,291",
      "irds_rate": "0",
      "hold_rate": "63.29",
      "method": "장내매수"
    },
    {
      "rcept_no": "20260527000051",
      "rcept_dt": "2026-05-27",
      "corp_name": "엑셈",
      "stock_code": "205100",
      "market": "KOSDAQ",
      "corp_code": "01042085",
      "repror": "조종암",
      "ofcps": "대표이사",
      "rgist": "등기임원",
      "main_shrholdr": "10%이상주주",
      "irds_cnt": "66,150",
      "total_cnt": "26,231,061",
      "irds_rate": "0.09",
      "hold_rate": "37.11",
      "method": "장내매수"
    },
    {
      "rcept_no": "20260527000031",
      "rcept_dt": "2026-05-27",
      "corp_name": "감성코퍼레이션",
      "stock_code": "036620",
      "market": "KOSDAQ",
      "corp_code": "00261009",
      "repror": "김호선",
      "ofcps": "대표이사",
      "rgist": "등기임원",
      "main_shrholdr": "10%이상주주",
      "irds_cnt": "50,000",
      "total_cnt": "22,000,000",
      "irds_rate": "0.06",
      "hold_rate": "24.31",
      "method": "장내매수"
    },
    {
      "rcept_no": "20260527000016",
      "rcept_dt": "2026-05-27",
      "corp_name": "드림씨아이에스",
      "stock_code": "223250",
      "market": "KOSDAQ",
      "corp_code": "00916826",
      "repror": "정재석",
      "ofcps": "상무",
      "rgist": "비등기임원",
      "main_shrholdr": "-",
      "irds_cnt": "2,000",
      "total_cnt": "2,000",
      "irds_rate": "0.01",
      "hold_rate": "0.01",
      "method": "장내매수"
    },
    {
      "rcept_no": "20260527000013",
      "rcept_dt": "2026-05-27",
      "corp_name": "드림씨아이에스",
      "stock_code": "223250",
      "market": "KOSDAQ",
      "corp_code": "00916826",
      "repror": "김경순",
      "ofcps": "부사장",
      "rgist": "등기임원",
      "main_shrholdr": "-",
      "irds_cnt": "1,975",
      "total_cnt": "1,975",
      "irds_rate": "0.01",
      "hold_rate": "0.01",
      "method": "장내매수"
    },
    {
      "rcept_no": "20260526000531",
      "rcept_dt": "2026-05-27",
      "corp_name": "에이치와이티씨",
      "stock_code": "148930",
      "market": "KOSDAQ",
      "corp_code": "00885906",
      "repror": "김욱현",
      "ofcps": "대표이사",
      "rgist": "등기임원",
      "main_shrholdr": "-",
      "irds_cnt": "2,000",
      "total_cnt": "9,838",
      "irds_rate": "0.02",
      "hold_rate": "0.10",
      "method": "장내매수"
    },
    {
      "rcept_no": "20260526000515",
      "rcept_dt": "2026-05-26",
      "corp_name": "티비씨",
      "stock_code": "033830",
      "market": "KOSDAQ",
      "corp_code": "00204642",
      "repror": "김한덕",
      "ofcps": "대표이사",
      "rgist": "등기임원",
      "main_shrholdr": "-",
      "irds_cnt": "20,000",
      "total_cnt": "20,000",
      "irds_rate": "0.02",
      "hold_rate": "0.02",
      "method": "장내매수"
    },
    {
      "rcept_no": "20260526000496",
      "rcept_dt": "2026-05-26",
      "corp_name": "에이텍모빌리티",
      "stock_code": "224110",
      "market": "KOSDAQ",
      "corp_code": "01099861",
      "repror": "신종찬",
      "ofcps": "이사",
      "rgist": "등기임원",
      "main_shrholdr": "-",
      "irds_cnt": "19,595",
      "total_cnt": "56,394",
      "irds_rate": "0.39",
      "hold_rate": "1.11",
      "method": "장내매수"
    },
    {
      "rcept_no": "20260526000488",
      "rcept_dt": "2026-05-26",
      "corp_name": "대신정보통신",
      "stock_code": "020180",
      "market": "KOSDAQ",
      "corp_code": "00110875",
      "repror": "강훈모",
      "ofcps": "전무이사",
      "rgist": "비등기임원",
      "main_shrholdr": "-",
      "irds_cnt": "17,405",
      "total_cnt": "17,405",
      "irds_rate": "0.04",
      "hold_rate": "0.04",
      "method": "장내매수"
    },
    {
      "rcept_no": "20260526000483",
      "rcept_dt": "2026-05-26",
      "corp_name": "대신정보통신",
      "stock_code": "020180",
      "market": "KOSDAQ",
      "corp_code": "00110875",
      "repror": "윤영민",
      "ofcps": "전무이사",
      "rgist": "비등기임원",
      "main_shrholdr": "-",
      "irds_cnt": "45,000",
      "total_cnt": "45,000",
      "irds_rate": "0.11",
      "hold_rate": "0.11",
      "method": "장내매수"
    },
    {
      "rcept_no": "20260526000477",
      "rcept_dt": "2026-05-26",
      "corp_name": "푸른저축은행",
      "stock_code": "007330",
      "market": "KOSDAQ",
      "corp_code": "00124805",
      "repror": "주신홍",
      "ofcps": "-",
      "rgist": "-",
      "main_shrholdr": "사실상지배주주",
      "irds_cnt": "589,320",
      "total_cnt": "3,186,823",
      "irds_rate": "3.91",
      "hold_rate": "21.13",
      "method": "시간외매매"
    },
    {
      "rcept_no": "20260526000476",
      "rcept_dt": "2026-05-26",
      "corp_name": "대신정보통신",
      "stock_code": "020180",
      "market": "KOSDAQ",
      "corp_code": "00110875",
      "repror": "양동해",
      "ofcps": "전무이사",
      "rgist": "비등기임원",
      "main_shrholdr": "-",
      "irds_cnt": "50,000",
      "total_cnt": "50,000",
      "irds_rate": "0.13",
      "hold_rate": "0.13",
      "method": "장내매수"
    },
    {
      "rcept_no": "20260526000470",
      "rcept_dt": "2026-05-26",
      "corp_name": "대신정보통신",
      "stock_code": "020180",
      "market": "KOSDAQ",
      "corp_code": "00110875",
      "repror": "원유석",
      "ofcps": "전무이사",
      "rgist": "비등기임원",
      "main_shrholdr": "-",
      "irds_cnt": "80,000",
      "total_cnt": "80,000",
      "irds_rate": "0.2",
      "hold_rate": "0.2",
      "method": "장내매수"
    },
    {
      "rcept_no": "20260526000445",
      "rcept_dt": "2026-05-26",
      "corp_name": "핑거",
      "stock_code": "163730",
      "market": "KOSDAQ",
      "corp_code": "01142075",
      "repror": "서룡전자",
      "ofcps": "-",
      "rgist": "-",
      "main_shrholdr": "사실상지배주주",
      "irds_cnt": "5,926,028",
      "total_cnt": "5,926,028",
      "irds_rate": "39.26",
      "hold_rate": "39.26",
      "method": "장외매수"
    },
    {
      "rcept_no": "20260526000441",
      "rcept_dt": "2026-05-26",
      "corp_name": "에이루트",
      "stock_code": "096690",
      "market": "KOSDAQ",
      "corp_code": "00608839",
      "repror": "서문동군",
      "ofcps": "대표이사",
      "rgist": "등기임원",
      "main_shrholdr": "-",
      "irds_cnt": "2,653",
      "total_cnt": "70,056",
      "irds_rate": "0.06",
      "hold_rate": "1.74",
      "method": "장내매수"
    },
    {
      "rcept_no": "20260526000435",
      "rcept_dt": "2026-05-26",
      "corp_name": "에이루트",
      "stock_code": "096690",
      "market": "KOSDAQ",
      "corp_code": "00608839",
      "repror": "이대성",
      "ofcps": "사내이사",
      "rgist": "등기임원",
      "main_shrholdr": "-",
      "irds_cnt": "5,122",
      "total_cnt": "40,384",
      "irds_rate": "0.12",
      "hold_rate": "1.00",
      "method": "장내매수"
    },
    {
      "rcept_no": "20260526000417",
      "rcept_dt": "2026-05-26",
      "corp_name": "더핑크퐁컴퍼니",
      "stock_code": "403850",
      "market": "KOSDAQ",
      "corp_code": "01138364",
      "repror": "김민석",
      "ofcps": "대표이사",
      "rgist": "등기임원",
      "main_shrholdr": "10%이상주주",
      "irds_cnt": "82,800",
      "total_cnt": "2,360,000",
      "irds_rate": "0.57",
      "hold_rate": "16.44",
      "method": "장내매수"
    },
    {
      "rcept_no": "20260526000402",
      "rcept_dt": "2026-05-26",
      "corp_name": "성호전자",
      "stock_code": "043260",
      "market": "KOSDAQ",
      "corp_code": "00317210",
      "repror": "서룡전자",
      "ofcps": "-",
      "rgist": "-",
      "main_shrholdr": "사실상지배주주",
      "irds_cnt": "13,922",
      "total_cnt": "27,284,015",
      "irds_rate": "0.02",
      "hold_rate": "38.47",
      "method": "장내매수"
    },
    {
      "rcept_no": "20260526000389",
      "rcept_dt": "2026-05-26",
      "corp_name": "SFA반도체",
      "stock_code": "036540",
      "market": "KOSDAQ",
      "corp_code": "00301246",
      "repror": "오성국",
      "ofcps": "상무이사",
      "rgist": "비등기임원",
      "main_shrholdr": "-",
      "irds_cnt": "1",
      "total_cnt": "1",
      "irds_rate": "0.00",
      "hold_rate": "0.00",
      "method": "장내매수"
    },
    {
      "rcept_no": "20260526000381",
      "rcept_dt": "2026-05-26",
      "corp_name": "나노신소재",
      "stock_code": "121600",
      "market": "KOSDAQ",
      "corp_code": "00439965",
      "repror": "박장우",
      "ofcps": "대표이사",
      "rgist": "등기임원",
      "main_shrholdr": "사실상지배주주",
      "irds_cnt": "164",
      "total_cnt": "2,437,627",
      "irds_rate": "-0.07",
      "hold_rate": "19.89",
      "method": "장내매수"
    },
    {
      "rcept_no": "20260526000363",
      "rcept_dt": "2026-05-26",
      "corp_name": "BYC",
      "stock_code": "001460",
      "market": "KOSPI",
      "corp_code": "00122579",
      "repror": "한승홀딩스",
      "ofcps": "-",
      "rgist": "-",
      "main_shrholdr": "10%이상주주",
      "irds_cnt": "1,057",
      "total_cnt": "944,496",
      "irds_rate": "0.01",
      "hold_rate": "11.24",
      "method": "장내매수"
    },
    {
      "rcept_no": "20260526000361",
      "rcept_dt": "2026-05-26",
      "corp_name": "저스템",
      "stock_code": "417840",
      "market": "KOSDAQ",
      "corp_code": "01383229",
      "repror": "안호상",
      "ofcps": "이사",
      "rgist": "비등기임원",
      "main_shrholdr": "-",
      "irds_cnt": "5,000",
      "total_cnt": "5,000",
      "irds_rate": "0.02",
      "hold_rate": "0.02",
      "method": "장내매수"
    },
    {
      "rcept_no": "20260526000358",
      "rcept_dt": "2026-05-26",
      "corp_name": "저스템",
      "stock_code": "417840",
      "market": "KOSDAQ",
      "corp_code": "01383229",
      "repror": "김선식",
      "ofcps": "부사장",
      "rgist": "비등기임원",
      "main_shrholdr": "-",
      "irds_cnt": "1,200",
      "total_cnt": "1,200",
      "irds_rate": "0.01",
      "hold_rate": "0.01",
      "method": "장내매수"
    },
    {
      "rcept_no": "20260526000345",
      "rcept_dt": "2026-05-26",
      "corp_name": "그리티",
      "stock_code": "204020",
      "market": "KOSDAQ",
      "corp_code": "00671978",
      "repror": "문영우",
      "ofcps": "대표이사",
      "rgist": "등기임원",
      "main_shrholdr": "사실상지배주주",
      "irds_cnt": "236,250",
      "total_cnt": "7,167,509",
      "irds_rate": "1.22",
      "hold_rate": "36.85",
      "method": "장내매수"
    },
    {
      "rcept_no": "20260526000306",
      "rcept_dt": "2026-05-26",
      "corp_name": "대한뉴팜",
      "stock_code": "054670",
      "market": "KOSDAQ",
      "corp_code": "00207375",
      "repror": "이원석",
      "ofcps": "대표이사",
      "rgist": "등기임원",
      "main_shrholdr": "-",
      "irds_cnt": "40,834",
      "total_cnt": "1,178,199",
      "irds_rate": "0.29",
      "hold_rate": "8.21",
      "method": "장내매수"
    },
    {
      "rcept_no": "20260526000289",
      "rcept_dt": "2026-05-26",
      "corp_name": "포인트엔지니어링",
      "stock_code": "256630",
      "market": "KOSDAQ",
      "corp_code": "01179608",
      "repror": "안범모",
      "ofcps": "대표이사",
      "rgist": "등기임원",
      "main_shrholdr": "사실상지배주주",
      "irds_cnt": "55,000",
      "total_cnt": "3,235,000",
      "irds_rate": "0.47",
      "hold_rate": "27.89",
      "method": "장내매수"
    },
    {
      "rcept_no": "20260526000274",
      "rcept_dt": "2026-05-26",
      "corp_name": "일월지엠엘",
      "stock_code": "178780",
      "market": "KOSDAQ",
      "corp_code": "00923826",
      "repror": "이광모",
      "ofcps": "대표이사",
      "rgist": "등기임원",
      "main_shrholdr": "-",
      "irds_cnt": "8,000",
      "total_cnt": "1,267,500",
      "irds_rate": "0.04",
      "hold_rate": "6.80",
      "method": "장내매수"
    },
    {
      "rcept_no": "20260526000244",
      "rcept_dt": "2026-05-26",
      "corp_name": "삼성전자",
      "stock_code": "005930",
      "market": "KOSPI",
      "corp_code": "00126380",
      "repror": "조미선",
      "ofcps": "상무",
      "rgist": "비등기임원",
      "main_shrholdr": "-",
      "irds_cnt": "120",
      "total_cnt": "3,409",
      "irds_rate": "0",
      "hold_rate": "0",
      "method": "장내매수"
    },
    {
      "rcept_no": "20260526000212",
      "rcept_dt": "2026-05-26",
      "corp_name": "한국주철관공업",
      "stock_code": "000970",
      "market": "KOSPI",
      "corp_code": "00159573",
      "repror": "김태형",
      "ofcps": "대표이사",
      "rgist": "등기임원",
      "main_shrholdr": "-",
      "irds_cnt": "54,106",
      "total_cnt": "2,022,715",
      "irds_rate": "0.24",
      "hold_rate": "8.87",
      "method": "장내매수"
    },
    {
      "rcept_no": "20260526000206",
      "rcept_dt": "2026-05-26",
      "corp_name": "가온전선",
      "stock_code": "000500",
      "market": "KOSPI",
      "corp_code": "00104768",
      "repror": "정현",
      "ofcps": "부사장\n(대표이사)",
      "rgist": "등기임원",
      "main_shrholdr": "-",
      "irds_cnt": "150",
      "total_cnt": "2,730",
      "irds_rate": "0.00",
      "hold_rate": "0.01",
      "method": "장내매수"
    },
    {
      "rcept_no": "20260526000191",
      "rcept_dt": "2026-05-26",
      "corp_name": "드림씨아이에스",
      "stock_code": "223250",
      "market": "KOSDAQ",
      "corp_code": "00916826",
      "repror": "유정희",
      "ofcps": "대표이사",
      "rgist": "등기임원",
      "main_shrholdr": "-",
      "irds_cnt": "26,400",
      "total_cnt": "1,287,472",
      "irds_rate": "0.10",
      "hold_rate": "5.23",
      "method": "장내매수"
    },
    {
      "rcept_no": "20260526000176",
      "rcept_dt": "2026-05-26",
      "corp_name": "케이옥션",
      "stock_code": "102370",
      "market": "KOSDAQ",
      "corp_code": "00668600",
      "repror": "티에이어드바이저",
      "ofcps": "-",
      "rgist": "-",
      "main_shrholdr": "10%이상주주",
      "irds_cnt": "136,548",
      "total_cnt": "13,579,312",
      "irds_rate": "0.50",
      "hold_rate": "49.87",
      "method": "장내매수"
    },
    {
      "rcept_no": "20260526000150",
      "rcept_dt": "2026-05-26",
      "corp_name": "대성미생물",
      "stock_code": "036480",
      "market": "KOSDAQ",
      "corp_code": "00177320",
      "repror": "최승훈",
      "ofcps": "대표이사",
      "rgist": "등기임원",
      "main_shrholdr": "-",
      "irds_cnt": "3,149",
      "total_cnt": "29,239",
      "irds_rate": "0.08",
      "hold_rate": "0.77",
      "method": "장내매수"
    },
    {
      "rcept_no": "20260526000141",
      "rcept_dt": "2026-05-26",
      "corp_name": "삼성전자",
      "stock_code": "005930",
      "market": "KOSPI",
      "corp_code": "00126380",
      "repror": "신용우",
      "ofcps": "상무",
      "rgist": "비등기임원",
      "main_shrholdr": "-",
      "irds_cnt": "50",
      "total_cnt": "836",
      "irds_rate": "0.00",
      "hold_rate": "0.00",
      "method": "장내매수"
    },
    {
      "rcept_no": "20260526000126",
      "rcept_dt": "2026-05-26",
      "corp_name": "대신정보통신",
      "stock_code": "020180",
      "market": "KOSDAQ",
      "corp_code": "00110875",
      "repror": "최현택",
      "ofcps": "대표이사",
      "rgist": "등기임원",
      "main_shrholdr": "-",
      "irds_cnt": "171,000",
      "total_cnt": "1,639,000",
      "irds_rate": "0.45",
      "hold_rate": "4.27",
      "method": "장내매수"
    },
    {
      "rcept_no": "20260526000115",
      "rcept_dt": "2026-05-26",
      "corp_name": "도화엔지니어링",
      "stock_code": "002150",
      "market": "KOSPI",
      "corp_code": "00114552",
      "repror": "손영일",
      "ofcps": "사장",
      "rgist": "등기임원",
      "main_shrholdr": "-",
      "irds_cnt": "5,000",
      "total_cnt": "75,000",
      "irds_rate": "0.01",
      "hold_rate": "0.22",
      "method": "장내매수"
    },
    {
      "rcept_no": "20260526000111",
      "rcept_dt": "2026-05-26",
      "corp_name": "TS트릴리온",
      "stock_code": "317240",
      "market": "KOSDAQ",
      "corp_code": "01353024",
      "repror": "김용채",
      "ofcps": "대표이사",
      "rgist": "등기임원",
      "main_shrholdr": "사실상지배주주",
      "irds_cnt": "30,000",
      "total_cnt": "53,000",
      "irds_rate": "0.10",
      "hold_rate": "0.18",
      "method": "장내매수"
    },
    {
      "rcept_no": "20260526000086",
      "rcept_dt": "2026-05-26",
      "corp_name": "디티앤씨",
      "stock_code": "187220",
      "market": "KOSDAQ",
      "corp_code": "00675594",
      "repror": "김윤상",
      "ofcps": "부사장",
      "rgist": "등기임원",
      "main_shrholdr": "-",
      "irds_cnt": "4,200",
      "total_cnt": "4,200",
      "irds_rate": "0.03",
      "hold_rate": "0.03",
      "method": "장내매수"
    },
    {
      "rcept_no": "20260526000062",
      "rcept_dt": "2026-05-26",
      "corp_name": "케이아이엔엑스",
      "stock_code": "093320",
      "market": "KOSDAQ",
      "corp_code": "00603348",
      "repror": "TheMiriStrategicEmergingMarketsFundLP",
      "ofcps": "-",
      "rgist": "-",
      "main_shrholdr": "10%이상주주",
      "irds_cnt": "10,700",
      "total_cnt": "790,482",
      "irds_rate": "0.22",
      "hold_rate": "16.20",
      "method": "장내매수"
    }
  ]
}