{
  "updated_at": "2026-07-08T02:39:22Z",
  "quotes": {
    "KOSPI": {
      "price": 7504.42,
      "prev_close": 8051.33,
      "change": -546.91,
      "change_pct": -6.79
    },
    "KOSDAQ": {
      "price": 797.98,
      "prev_close": 847.07,
      "change": -49.09,
      "change_pct": -5.8
    },
    "S&P 500": {
      "price": 7503.85,
      "prev_close": 7483.24,
      "change": 20.61,
      "change_pct": 0.28
    },
    "USD/KRW": {
      "price": 1511.88,
      "prev_close": 1528.76,
      "change": -16.88,
      "change_pct": -1.1
    }
  }
}